[{"shape_pt_lat": "30.223303", "shape_id": "39068", "shape_pt_lon": "-97.765972", "shape_pt_sequence": "1", "shape_dist_traveled": "0.0000"}, {"shape_pt_lat": "30.223250", "shape_id": "39068", "shape_pt_lon": "-97.766003", "shape_pt_sequence": "2", "shape_dist_traveled": "0.0067"}, {"shape_pt_lat": "30.222856", "shape_id": "39068", "shape_pt_lon": "-97.766307", "shape_pt_sequence": "3", "shape_dist_traveled": "0.0594"}, {"shape_pt_lat": "30.222260", "shape_id": "39068", "shape_pt_lon": "-97.766667", "shape_pt_sequence": "4", "shape_dist_traveled": "0.1341"}, {"shape_pt_lat": "30.221735", "shape_id": "39068", "shape_pt_lon": "-97.765557", "shape_pt_sequence": "5", "shape_dist_traveled": "0.2558"}, {"shape_pt_lat": "30.221425", "shape_id": "39068", "shape_pt_lon": "-97.764876", "shape_pt_sequence": "6", "shape_dist_traveled": "0.3296"}, {"shape_pt_lat": "30.221871", "shape_id": "39068", "shape_pt_lon": "-97.764585", "shape_pt_sequence": "7", "shape_dist_traveled": "0.3870"}, {"shape_pt_lat": "30.221945", "shape_id": "39068", "shape_pt_lon": "-97.764537", "shape_pt_sequence": "8", "shape_dist_traveled": "0.3964"}, {"shape_pt_lat": "30.222027", "shape_id": "39068", "shape_pt_lon": "-97.764481", "shape_pt_sequence": "9", "shape_dist_traveled": "0.4067"}, {"shape_pt_lat": "30.222087", "shape_id": "39068", "shape_pt_lon": "-97.764440", "shape_pt_sequence": "10", "shape_dist_traveled": "0.4147"}, {"shape_pt_lat": "30.222349", "shape_id": "39068", "shape_pt_lon": "-97.764272", "shape_pt_sequence": "11", "shape_dist_traveled": "0.4479"}, {"shape_pt_lat": "30.222502", "shape_id": "39068", "shape_pt_lon": "-97.764181", "shape_pt_sequence": "12", "shape_dist_traveled": "0.4671"}, {"shape_pt_lat": "30.222780", "shape_id": "39068", "shape_pt_lon": "-97.764011", "shape_pt_sequence": "13", "shape_dist_traveled": "0.5020"}, {"shape_pt_lat": "30.222860", "shape_id": "39068", "shape_pt_lon": "-97.763959", "shape_pt_sequence": "14", "shape_dist_traveled": "0.5123"}, {"shape_pt_lat": "30.223018", "shape_id": "39068", "shape_pt_lon": "-97.763864", "shape_pt_sequence": "15", "shape_dist_traveled": "0.5315"}, {"shape_pt_lat": "30.223061", "shape_id": "39068", "shape_pt_lon": "-97.763837", "shape_pt_sequence": "16", "shape_dist_traveled": "0.5373"}, {"shape_pt_lat": "30.223309", "shape_id": "39068", "shape_pt_lon": "-97.763691", "shape_pt_sequence": "17", "shape_dist_traveled": "0.5678"}, {"shape_pt_lat": "30.223434", "shape_id": "39068", "shape_pt_lon": "-97.763614", "shape_pt_sequence": "18", "shape_dist_traveled": "0.5834"}, {"shape_pt_lat": "30.223626", "shape_id": "39068", "shape_pt_lon": "-97.763887", "shape_pt_sequence": "19", "shape_dist_traveled": "0.6175"}, {"shape_pt_lat": "30.223700", "shape_id": "39068", "shape_pt_lon": "-97.763995", "shape_pt_sequence": "20", "shape_dist_traveled": "0.6303"}, {"shape_pt_lat": "30.223737", "shape_id": "39068", "shape_pt_lon": "-97.764059", "shape_pt_sequence": "21", "shape_dist_traveled": "0.6375"}, {"shape_pt_lat": "30.223862", "shape_id": "39068", "shape_pt_lon": "-97.764251", "shape_pt_sequence": "22", "shape_dist_traveled": "0.6611"}, {"shape_pt_lat": "30.223933", "shape_id": "39068", "shape_pt_lon": "-97.764363", "shape_pt_sequence": "23", "shape_dist_traveled": "0.6739"}, {"shape_pt_lat": "30.224099", "shape_id": "39068", "shape_pt_lon": "-97.764625", "shape_pt_sequence": "24", "shape_dist_traveled": "0.7055"}, {"shape_pt_lat": "30.224217", "shape_id": "39068", "shape_pt_lon": "-97.764807", "shape_pt_sequence": "25", "shape_dist_traveled": "0.7269"}, {"shape_pt_lat": "30.224486", "shape_id": "39068", "shape_pt_lon": "-97.765208", "shape_pt_sequence": "26", "shape_dist_traveled": "0.7761"}, {"shape_pt_lat": "30.224843", "shape_id": "39068", "shape_pt_lon": "-97.765715", "shape_pt_sequence": "27", "shape_dist_traveled": "0.8386"}, {"shape_pt_lat": "30.225550", "shape_id": "39068", "shape_pt_lon": "-97.766770", "shape_pt_sequence": "28", "shape_dist_traveled": "0.9670"}, {"shape_pt_lat": "30.225693", "shape_id": "39068", "shape_pt_lon": "-97.766995", "shape_pt_sequence": "29", "shape_dist_traveled": "0.9934"}, {"shape_pt_lat": "30.225814", "shape_id": "39068", "shape_pt_lon": "-97.767192", "shape_pt_sequence": "30", "shape_dist_traveled": "1.0170"}, {"shape_pt_lat": "30.225989", "shape_id": "39068", "shape_pt_lon": "-97.767481", "shape_pt_sequence": "31", "shape_dist_traveled": "1.0509"}, {"shape_pt_lat": "30.226071", "shape_id": "39068", "shape_pt_lon": "-97.767629", "shape_pt_sequence": "32", "shape_dist_traveled": "1.0675"}, {"shape_pt_lat": "30.226161", "shape_id": "39068", "shape_pt_lon": "-97.767795", "shape_pt_sequence": "33", "shape_dist_traveled": "1.0864"}, {"shape_pt_lat": "30.226184", "shape_id": "39068", "shape_pt_lon": "-97.767836", "shape_pt_sequence": "34", "shape_dist_traveled": "1.0914"}, {"shape_pt_lat": "30.226317", "shape_id": "39068", "shape_pt_lon": "-97.768087", "shape_pt_sequence": "35", "shape_dist_traveled": "1.1197"}, {"shape_pt_lat": "30.226366", "shape_id": "39068", "shape_pt_lon": "-97.768185", "shape_pt_sequence": "36", "shape_dist_traveled": "1.1308"}, {"shape_pt_lat": "30.226452", "shape_id": "39068", "shape_pt_lon": "-97.768354", "shape_pt_sequence": "37", "shape_dist_traveled": "1.1497"}, {"shape_pt_lat": "30.226599", "shape_id": "39068", "shape_pt_lon": "-97.768660", "shape_pt_sequence": "38", "shape_dist_traveled": "1.1828"}, {"shape_pt_lat": "30.226852", "shape_id": "39068", "shape_pt_lon": "-97.769160", "shape_pt_sequence": "39", "shape_dist_traveled": "1.2384"}, {"shape_pt_lat": "30.226899", "shape_id": "39068", "shape_pt_lon": "-97.769263", "shape_pt_sequence": "40", "shape_dist_traveled": "1.2496"}, {"shape_pt_lat": "30.226917", "shape_id": "39068", "shape_pt_lon": "-97.769302", "shape_pt_sequence": "41", "shape_dist_traveled": "1.2541"}, {"shape_pt_lat": "30.227177", "shape_id": "39068", "shape_pt_lon": "-97.769867", "shape_pt_sequence": "42", "shape_dist_traveled": "1.3153"}, {"shape_pt_lat": "30.227427", "shape_id": "39068", "shape_pt_lon": "-97.770387", "shape_pt_sequence": "43", "shape_dist_traveled": "1.3727"}, {"shape_pt_lat": "30.227443", "shape_id": "39068", "shape_pt_lon": "-97.770437", "shape_pt_sequence": "44", "shape_dist_traveled": "1.3780"}, {"shape_pt_lat": "30.227526", "shape_id": "39068", "shape_pt_lon": "-97.770608", "shape_pt_sequence": "45", "shape_dist_traveled": "1.3964"}, {"shape_pt_lat": "30.227690", "shape_id": "39068", "shape_pt_lon": "-97.770991", "shape_pt_sequence": "46", "shape_dist_traveled": "1.4375"}, {"shape_pt_lat": "30.227747", "shape_id": "39068", "shape_pt_lon": "-97.771154", "shape_pt_sequence": "47", "shape_dist_traveled": "1.4550"}, {"shape_pt_lat": "30.227776", "shape_id": "39068", "shape_pt_lon": "-97.771237", "shape_pt_sequence": "48", "shape_dist_traveled": "1.4636"}, {"shape_pt_lat": "30.227828", "shape_id": "39068", "shape_pt_lon": "-97.771387", "shape_pt_sequence": "49", "shape_dist_traveled": "1.4788"}, {"shape_pt_lat": "30.227877", "shape_id": "39068", "shape_pt_lon": "-97.771553", "shape_pt_sequence": "50", "shape_dist_traveled": "1.4955"}, {"shape_pt_lat": "30.227924", "shape_id": "39068", "shape_pt_lon": "-97.771699", "shape_pt_sequence": "51", "shape_dist_traveled": "1.5104"}, {"shape_pt_lat": "30.227939", "shape_id": "39068", "shape_pt_lon": "-97.771748", "shape_pt_sequence": "52", "shape_dist_traveled": "1.5158"}, {"shape_pt_lat": "30.227964", "shape_id": "39068", "shape_pt_lon": "-97.771842", "shape_pt_sequence": "53", "shape_dist_traveled": "1.5253"}, {"shape_pt_lat": "30.227988", "shape_id": "39068", "shape_pt_lon": "-97.771930", "shape_pt_sequence": "54", "shape_dist_traveled": "1.5338"}, {"shape_pt_lat": "30.228005", "shape_id": "39068", "shape_pt_lon": "-97.772007", "shape_pt_sequence": "55", "shape_dist_traveled": "1.5419"}, {"shape_pt_lat": "30.228065", "shape_id": "39068", "shape_pt_lon": "-97.772326", "shape_pt_sequence": "56", "shape_dist_traveled": "1.5727"}, {"shape_pt_lat": "30.228109", "shape_id": "39068", "shape_pt_lon": "-97.772611", "shape_pt_sequence": "57", "shape_dist_traveled": "1.6011"}, {"shape_pt_lat": "30.228137", "shape_id": "39068", "shape_pt_lon": "-97.772891", "shape_pt_sequence": "58", "shape_dist_traveled": "1.6283"}, {"shape_pt_lat": "30.228150", "shape_id": "39068", "shape_pt_lon": "-97.773102", "shape_pt_sequence": "59", "shape_dist_traveled": "1.6484"}, {"shape_pt_lat": "30.228162", "shape_id": "39068", "shape_pt_lon": "-97.773411", "shape_pt_sequence": "60", "shape_dist_traveled": "1.6784"}, {"shape_pt_lat": "30.228158", "shape_id": "39068", "shape_pt_lon": "-97.773766", "shape_pt_sequence": "61", "shape_dist_traveled": "1.7124"}, {"shape_pt_lat": "30.228137", "shape_id": "39068", "shape_pt_lon": "-97.774155", "shape_pt_sequence": "62", "shape_dist_traveled": "1.7495"}, {"shape_pt_lat": "30.228103", "shape_id": "39068", "shape_pt_lon": "-97.774627", "shape_pt_sequence": "63", "shape_dist_traveled": "1.7956"}, {"shape_pt_lat": "30.228037", "shape_id": "39068", "shape_pt_lon": "-97.775472", "shape_pt_sequence": "64", "shape_dist_traveled": "1.8770"}, {"shape_pt_lat": "30.228011", "shape_id": "39068", "shape_pt_lon": "-97.775908", "shape_pt_sequence": "65", "shape_dist_traveled": "1.9191"}, {"shape_pt_lat": "30.228003", "shape_id": "39068", "shape_pt_lon": "-97.776192", "shape_pt_sequence": "66", "shape_dist_traveled": "1.9461"}, {"shape_pt_lat": "30.228001", "shape_id": "39068", "shape_pt_lon": "-97.776337", "shape_pt_sequence": "67", "shape_dist_traveled": "1.9602"}, {"shape_pt_lat": "30.228004", "shape_id": "39068", "shape_pt_lon": "-97.776404", "shape_pt_sequence": "68", "shape_dist_traveled": "1.9663"}, {"shape_pt_lat": "30.228064", "shape_id": "39068", "shape_pt_lon": "-97.778024", "shape_pt_sequence": "69", "shape_dist_traveled": "2.1224"}, {"shape_pt_lat": "30.228098", "shape_id": "39068", "shape_pt_lon": "-97.778787", "shape_pt_sequence": "70", "shape_dist_traveled": "2.1955"}, {"shape_pt_lat": "30.228113", "shape_id": "39068", "shape_pt_lon": "-97.779124", "shape_pt_sequence": "71", "shape_dist_traveled": "2.2285"}, {"shape_pt_lat": "30.228151", "shape_id": "39068", "shape_pt_lon": "-97.779971", "shape_pt_sequence": "72", "shape_dist_traveled": "2.3096"}, {"shape_pt_lat": "30.228189", "shape_id": "39068", "shape_pt_lon": "-97.780917", "shape_pt_sequence": "73", "shape_dist_traveled": "2.4008"}, {"shape_pt_lat": "30.228201", "shape_id": "39068", "shape_pt_lon": "-97.781227", "shape_pt_sequence": "74", "shape_dist_traveled": "2.4308"}, {"shape_pt_lat": "30.228207", "shape_id": "39068", "shape_pt_lon": "-97.781405", "shape_pt_sequence": "75", "shape_dist_traveled": "2.4478"}, {"shape_pt_lat": "30.228217", "shape_id": "39068", "shape_pt_lon": "-97.781555", "shape_pt_sequence": "76", "shape_dist_traveled": "2.4629"}, {"shape_pt_lat": "30.228230", "shape_id": "39068", "shape_pt_lon": "-97.781728", "shape_pt_sequence": "77", "shape_dist_traveled": "2.4789"}, {"shape_pt_lat": "30.228246", "shape_id": "39068", "shape_pt_lon": "-97.781868", "shape_pt_sequence": "78", "shape_dist_traveled": "2.4930"}, {"shape_pt_lat": "30.228263", "shape_id": "39068", "shape_pt_lon": "-97.782016", "shape_pt_sequence": "79", "shape_dist_traveled": "2.5072"}, {"shape_pt_lat": "30.228286", "shape_id": "39068", "shape_pt_lon": "-97.782153", "shape_pt_sequence": "80", "shape_dist_traveled": "2.5205"}, {"shape_pt_lat": "30.228352", "shape_id": "39068", "shape_pt_lon": "-97.782481", "shape_pt_sequence": "81", "shape_dist_traveled": "2.5533"}, {"shape_pt_lat": "30.228424", "shape_id": "39068", "shape_pt_lon": "-97.782785", "shape_pt_sequence": "82", "shape_dist_traveled": "2.5834"}, {"shape_pt_lat": "30.228488", "shape_id": "39068", "shape_pt_lon": "-97.783091", "shape_pt_sequence": "83", "shape_dist_traveled": "2.6132"}, {"shape_pt_lat": "30.228572", "shape_id": "39068", "shape_pt_lon": "-97.783422", "shape_pt_sequence": "84", "shape_dist_traveled": "2.6464"}, {"shape_pt_lat": "30.228655", "shape_id": "39068", "shape_pt_lon": "-97.783787", "shape_pt_sequence": "85", "shape_dist_traveled": "2.6828"}, {"shape_pt_lat": "30.228732", "shape_id": "39068", "shape_pt_lon": "-97.784094", "shape_pt_sequence": "86", "shape_dist_traveled": "2.7129"}, {"shape_pt_lat": "30.228873", "shape_id": "39068", "shape_pt_lon": "-97.784642", "shape_pt_sequence": "87", "shape_dist_traveled": "2.7683"}, {"shape_pt_lat": "30.228953", "shape_id": "39068", "shape_pt_lon": "-97.784940", "shape_pt_sequence": "88", "shape_dist_traveled": "2.7986"}, {"shape_pt_lat": "30.229021", "shape_id": "39068", "shape_pt_lon": "-97.785165", "shape_pt_sequence": "89", "shape_dist_traveled": "2.8208"}, {"shape_pt_lat": "30.229069", "shape_id": "39068", "shape_pt_lon": "-97.785324", "shape_pt_sequence": "90", "shape_dist_traveled": "2.8379"}, {"shape_pt_lat": "30.229170", "shape_id": "39068", "shape_pt_lon": "-97.785582", "shape_pt_sequence": "91", "shape_dist_traveled": "2.8643"}, {"shape_pt_lat": "30.229222", "shape_id": "39068", "shape_pt_lon": "-97.785703", "shape_pt_sequence": "92", "shape_dist_traveled": "2.8777"}, {"shape_pt_lat": "30.229329", "shape_id": "39068", "shape_pt_lon": "-97.785957", "shape_pt_sequence": "93", "shape_dist_traveled": "2.9045"}, {"shape_pt_lat": "30.229582", "shape_id": "39068", "shape_pt_lon": "-97.786489", "shape_pt_sequence": "94", "shape_dist_traveled": "2.9636"}, {"shape_pt_lat": "30.229774", "shape_id": "39068", "shape_pt_lon": "-97.786893", "shape_pt_sequence": "95", "shape_dist_traveled": "3.0070"}, {"shape_pt_lat": "30.229925", "shape_id": "39068", "shape_pt_lon": "-97.787205", "shape_pt_sequence": "96", "shape_dist_traveled": "3.0415"}, {"shape_pt_lat": "30.230084", "shape_id": "39068", "shape_pt_lon": "-97.787570", "shape_pt_sequence": "97", "shape_dist_traveled": "3.0808"}, {"shape_pt_lat": "30.230320", "shape_id": "39068", "shape_pt_lon": "-97.788063", "shape_pt_sequence": "98", "shape_dist_traveled": "3.1354"}, {"shape_pt_lat": "30.230349", "shape_id": "39068", "shape_pt_lon": "-97.788122", "shape_pt_sequence": "99", "shape_dist_traveled": "3.1413"}, {"shape_pt_lat": "30.230385", "shape_id": "39068", "shape_pt_lon": "-97.788197", "shape_pt_sequence": "100", "shape_dist_traveled": "3.1502"}, {"shape_pt_lat": "30.230458", "shape_id": "39068", "shape_pt_lon": "-97.788350", "shape_pt_sequence": "101", "shape_dist_traveled": "3.1663"}, {"shape_pt_lat": "30.230543", "shape_id": "39068", "shape_pt_lon": "-97.788517", "shape_pt_sequence": "102", "shape_dist_traveled": "3.1852"}, {"shape_pt_lat": "30.230719", "shape_id": "39068", "shape_pt_lon": "-97.788882", "shape_pt_sequence": "103", "shape_dist_traveled": "3.2250"}, {"shape_pt_lat": "30.231064", "shape_id": "39068", "shape_pt_lon": "-97.789585", "shape_pt_sequence": "104", "shape_dist_traveled": "3.3034"}, {"shape_pt_lat": "30.231601", "shape_id": "39068", "shape_pt_lon": "-97.790694", "shape_pt_sequence": "105", "shape_dist_traveled": "3.4256"}, {"shape_pt_lat": "30.231643", "shape_id": "39068", "shape_pt_lon": "-97.790782", "shape_pt_sequence": "106", "shape_dist_traveled": "3.4350"}, {"shape_pt_lat": "30.231871", "shape_id": "39068", "shape_pt_lon": "-97.791259", "shape_pt_sequence": "107", "shape_dist_traveled": "3.4879"}, {"shape_pt_lat": "30.231992", "shape_id": "39068", "shape_pt_lon": "-97.791512", "shape_pt_sequence": "108", "shape_dist_traveled": "3.5152"}, {"shape_pt_lat": "30.231892", "shape_id": "39068", "shape_pt_lon": "-97.791575", "shape_pt_sequence": "109", "shape_dist_traveled": "3.5277"}, {"shape_pt_lat": "30.231745", "shape_id": "39068", "shape_pt_lon": "-97.791659", "shape_pt_sequence": "110", "shape_dist_traveled": "3.5456"}, {"shape_pt_lat": "30.231542", "shape_id": "39068", "shape_pt_lon": "-97.791785", "shape_pt_sequence": "111", "shape_dist_traveled": "3.5715"}, {"shape_pt_lat": "30.231432", "shape_id": "39068", "shape_pt_lon": "-97.791860", "shape_pt_sequence": "112", "shape_dist_traveled": "3.5859"}, {"shape_pt_lat": "30.231290", "shape_id": "39068", "shape_pt_lon": "-97.791949", "shape_pt_sequence": "113", "shape_dist_traveled": "3.6038"}, {"shape_pt_lat": "30.229900", "shape_id": "39068", "shape_pt_lon": "-97.792803", "shape_pt_sequence": "114", "shape_dist_traveled": "3.7783"}, {"shape_pt_lat": "30.230289", "shape_id": "39068", "shape_pt_lon": "-97.793516", "shape_pt_sequence": "115", "shape_dist_traveled": "3.8596"}, {"shape_pt_lat": "30.230412", "shape_id": "39068", "shape_pt_lon": "-97.793829", "shape_pt_sequence": "116", "shape_dist_traveled": "3.8927"}, {"shape_pt_lat": "30.230451", "shape_id": "39068", "shape_pt_lon": "-97.794010", "shape_pt_sequence": "117", "shape_dist_traveled": "3.9102"}, {"shape_pt_lat": "30.230462", "shape_id": "39068", "shape_pt_lon": "-97.794204", "shape_pt_sequence": "118", "shape_dist_traveled": "3.9292"}, {"shape_pt_lat": "30.230418", "shape_id": "39068", "shape_pt_lon": "-97.794604", "shape_pt_sequence": "119", "shape_dist_traveled": "3.9674"}, {"shape_pt_lat": "30.230365", "shape_id": "39068", "shape_pt_lon": "-97.794842", "shape_pt_sequence": "120", "shape_dist_traveled": "3.9912"}, {"shape_pt_lat": "30.230181", "shape_id": "39068", "shape_pt_lon": "-97.795326", "shape_pt_sequence": "121", "shape_dist_traveled": "4.0427"}, {"shape_pt_lat": "30.230009", "shape_id": "39068", "shape_pt_lon": "-97.795852", "shape_pt_sequence": "122", "shape_dist_traveled": "4.0961"}, {"shape_pt_lat": "30.229814", "shape_id": "39068", "shape_pt_lon": "-97.796295", "shape_pt_sequence": "123", "shape_dist_traveled": "4.1440"}, {"shape_pt_lat": "30.229745", "shape_id": "39068", "shape_pt_lon": "-97.796546", "shape_pt_sequence": "124", "shape_dist_traveled": "4.1693"}, {"shape_pt_lat": "30.229729", "shape_id": "39068", "shape_pt_lon": "-97.796669", "shape_pt_sequence": "125", "shape_dist_traveled": "4.1815"}, {"shape_pt_lat": "30.229730", "shape_id": "39068", "shape_pt_lon": "-97.796761", "shape_pt_sequence": "126", "shape_dist_traveled": "4.1905"}, {"shape_pt_lat": "30.229749", "shape_id": "39068", "shape_pt_lon": "-97.796904", "shape_pt_sequence": "127", "shape_dist_traveled": "4.2048"}, {"shape_pt_lat": "30.229783", "shape_id": "39068", "shape_pt_lon": "-97.797054", "shape_pt_sequence": "128", "shape_dist_traveled": "4.2191"}, {"shape_pt_lat": "30.230099", "shape_id": "39068", "shape_pt_lon": "-97.797483", "shape_pt_sequence": "129", "shape_dist_traveled": "4.2730"}, {"shape_pt_lat": "30.230156", "shape_id": "39068", "shape_pt_lon": "-97.797608", "shape_pt_sequence": "130", "shape_dist_traveled": "4.2869"}, {"shape_pt_lat": "30.230197", "shape_id": "39068", "shape_pt_lon": "-97.797781", "shape_pt_sequence": "131", "shape_dist_traveled": "4.3044"}, {"shape_pt_lat": "30.230197", "shape_id": "39068", "shape_pt_lon": "-97.797953", "shape_pt_sequence": "132", "shape_dist_traveled": "4.3204"}, {"shape_pt_lat": "30.230136", "shape_id": "39068", "shape_pt_lon": "-97.798249", "shape_pt_sequence": "133", "shape_dist_traveled": "4.3500"}, {"shape_pt_lat": "30.230069", "shape_id": "39068", "shape_pt_lon": "-97.798359", "shape_pt_sequence": "134", "shape_dist_traveled": "4.3628"}, {"shape_pt_lat": "30.229972", "shape_id": "39068", "shape_pt_lon": "-97.798478", "shape_pt_sequence": "135", "shape_dist_traveled": "4.3791"}, {"shape_pt_lat": "30.229572", "shape_id": "39068", "shape_pt_lon": "-97.798861", "shape_pt_sequence": "136", "shape_dist_traveled": "4.4366"}, {"shape_pt_lat": "30.229383", "shape_id": "39068", "shape_pt_lon": "-97.799064", "shape_pt_sequence": "137", "shape_dist_traveled": "4.4649"}, {"shape_pt_lat": "30.229268", "shape_id": "39068", "shape_pt_lon": "-97.799225", "shape_pt_sequence": "138", "shape_dist_traveled": "4.4855"}, {"shape_pt_lat": "30.229178", "shape_id": "39068", "shape_pt_lon": "-97.799387", "shape_pt_sequence": "139", "shape_dist_traveled": "4.5035"}, {"shape_pt_lat": "30.229117", "shape_id": "39068", "shape_pt_lon": "-97.799533", "shape_pt_sequence": "140", "shape_dist_traveled": "4.5187"}, {"shape_pt_lat": "30.229101", "shape_id": "39068", "shape_pt_lon": "-97.799604", "shape_pt_sequence": "141", "shape_dist_traveled": "4.5260"}, {"shape_pt_lat": "30.229086", "shape_id": "39068", "shape_pt_lon": "-97.799688", "shape_pt_sequence": "142", "shape_dist_traveled": "4.5343"}, {"shape_pt_lat": "30.229077", "shape_id": "39068", "shape_pt_lon": "-97.799775", "shape_pt_sequence": "143", "shape_dist_traveled": "4.5433"}, {"shape_pt_lat": "30.229067", "shape_id": "39068", "shape_pt_lon": "-97.799889", "shape_pt_sequence": "144", "shape_dist_traveled": "4.5544"}, {"shape_pt_lat": "30.229063", "shape_id": "39068", "shape_pt_lon": "-97.800030", "shape_pt_sequence": "145", "shape_dist_traveled": "4.5674"}, {"shape_pt_lat": "30.229041", "shape_id": "39068", "shape_pt_lon": "-97.800424", "shape_pt_sequence": "146", "shape_dist_traveled": "4.6055"}, {"shape_pt_lat": "30.229035", "shape_id": "39068", "shape_pt_lon": "-97.800510", "shape_pt_sequence": "147", "shape_dist_traveled": "4.6135"}, {"shape_pt_lat": "30.229028", "shape_id": "39068", "shape_pt_lon": "-97.800609", "shape_pt_sequence": "148", "shape_dist_traveled": "4.6235"}, {"shape_pt_lat": "30.229022", "shape_id": "39068", "shape_pt_lon": "-97.800707", "shape_pt_sequence": "149", "shape_dist_traveled": "4.6326"}, {"shape_pt_lat": "30.229020", "shape_id": "39068", "shape_pt_lon": "-97.800782", "shape_pt_sequence": "150", "shape_dist_traveled": "4.6396"}, {"shape_pt_lat": "30.229022", "shape_id": "39068", "shape_pt_lon": "-97.800860", "shape_pt_sequence": "151", "shape_dist_traveled": "4.6476"}, {"shape_pt_lat": "30.229025", "shape_id": "39068", "shape_pt_lon": "-97.800934", "shape_pt_sequence": "152", "shape_dist_traveled": "4.6547"}, {"shape_pt_lat": "30.229029", "shape_id": "39068", "shape_pt_lon": "-97.801006", "shape_pt_sequence": "153", "shape_dist_traveled": "4.6617"}, {"shape_pt_lat": "30.229048", "shape_id": "39068", "shape_pt_lon": "-97.801086", "shape_pt_sequence": "154", "shape_dist_traveled": "4.6699"}, {"shape_pt_lat": "30.229069", "shape_id": "39068", "shape_pt_lon": "-97.801149", "shape_pt_sequence": "155", "shape_dist_traveled": "4.6766"}, {"shape_pt_lat": "30.229114", "shape_id": "39068", "shape_pt_lon": "-97.801248", "shape_pt_sequence": "156", "shape_dist_traveled": "4.6869"}, {"shape_pt_lat": "30.229204", "shape_id": "39068", "shape_pt_lon": "-97.801209", "shape_pt_sequence": "157", "shape_dist_traveled": "4.6977"}, {"shape_pt_lat": "30.229338", "shape_id": "39068", "shape_pt_lon": "-97.801162", "shape_pt_sequence": "158", "shape_dist_traveled": "4.7123"}, {"shape_pt_lat": "30.229444", "shape_id": "39068", "shape_pt_lon": "-97.801129", "shape_pt_sequence": "159", "shape_dist_traveled": "4.7246"}, {"shape_pt_lat": "30.230694", "shape_id": "39068", "shape_pt_lon": "-97.800741", "shape_pt_sequence": "160", "shape_dist_traveled": "4.8687"}, {"shape_pt_lat": "30.230817", "shape_id": "39068", "shape_pt_lon": "-97.800705", "shape_pt_sequence": "161", "shape_dist_traveled": "4.8830"}, {"shape_pt_lat": "30.230953", "shape_id": "39068", "shape_pt_lon": "-97.800662", "shape_pt_sequence": "162", "shape_dist_traveled": "4.8986"}, {"shape_pt_lat": "30.231026", "shape_id": "39068", "shape_pt_lon": "-97.800642", "shape_pt_sequence": "163", "shape_dist_traveled": "4.9068"}, {"shape_pt_lat": "30.231192", "shape_id": "39068", "shape_pt_lon": "-97.800597", "shape_pt_sequence": "164", "shape_dist_traveled": "4.9255"}, {"shape_pt_lat": "30.231291", "shape_id": "39068", "shape_pt_lon": "-97.800582", "shape_pt_sequence": "165", "shape_dist_traveled": "4.9365"}, {"shape_pt_lat": "30.231463", "shape_id": "39068", "shape_pt_lon": "-97.800555", "shape_pt_sequence": "166", "shape_dist_traveled": "4.9558"}, {"shape_pt_lat": "30.231589", "shape_id": "39068", "shape_pt_lon": "-97.800543", "shape_pt_sequence": "167", "shape_dist_traveled": "4.9698"}, {"shape_pt_lat": "30.231697", "shape_id": "39068", "shape_pt_lon": "-97.800537", "shape_pt_sequence": "168", "shape_dist_traveled": "4.9818"}, {"shape_pt_lat": "30.231995", "shape_id": "39068", "shape_pt_lon": "-97.800546", "shape_pt_sequence": "169", "shape_dist_traveled": "5.0148"}, {"shape_pt_lat": "30.232066", "shape_id": "39068", "shape_pt_lon": "-97.800549", "shape_pt_sequence": "170", "shape_dist_traveled": "5.0229"}, {"shape_pt_lat": "30.232144", "shape_id": "39068", "shape_pt_lon": "-97.800560", "shape_pt_sequence": "171", "shape_dist_traveled": "5.0319"}, {"shape_pt_lat": "30.232370", "shape_id": "39068", "shape_pt_lon": "-97.800602", "shape_pt_sequence": "172", "shape_dist_traveled": "5.0572"}, {"shape_pt_lat": "30.232559", "shape_id": "39068", "shape_pt_lon": "-97.800640", "shape_pt_sequence": "173", "shape_dist_traveled": "5.0785"}, {"shape_pt_lat": "30.232636", "shape_id": "39068", "shape_pt_lon": "-97.800667", "shape_pt_sequence": "174", "shape_dist_traveled": "5.0879"}, {"shape_pt_lat": "30.232721", "shape_id": "39068", "shape_pt_lon": "-97.800688", "shape_pt_sequence": "175", "shape_dist_traveled": "5.0972"}, {"shape_pt_lat": "30.232769", "shape_id": "39068", "shape_pt_lon": "-97.800704", "shape_pt_sequence": "176", "shape_dist_traveled": "5.1023"}, {"shape_pt_lat": "30.232815", "shape_id": "39068", "shape_pt_lon": "-97.800717", "shape_pt_sequence": "177", "shape_dist_traveled": "5.1076"}, {"shape_pt_lat": "30.232936", "shape_id": "39068", "shape_pt_lon": "-97.800745", "shape_pt_sequence": "178", "shape_dist_traveled": "5.1218"}, {"shape_pt_lat": "30.232881", "shape_id": "39068", "shape_pt_lon": "-97.800960", "shape_pt_sequence": "179", "shape_dist_traveled": "5.1436"}, {"shape_pt_lat": "30.232830", "shape_id": "39068", "shape_pt_lon": "-97.801179", "shape_pt_sequence": "180", "shape_dist_traveled": "5.1655"}, {"shape_pt_lat": "30.232760", "shape_id": "39068", "shape_pt_lon": "-97.801511", "shape_pt_sequence": "181", "shape_dist_traveled": "5.1985"}, {"shape_pt_lat": "30.232643", "shape_id": "39068", "shape_pt_lon": "-97.802093", "shape_pt_sequence": "182", "shape_dist_traveled": "5.2559"}, {"shape_pt_lat": "30.232444", "shape_id": "39068", "shape_pt_lon": "-97.802971", "shape_pt_sequence": "183", "shape_dist_traveled": "5.3428"}, {"shape_pt_lat": "30.232394", "shape_id": "39068", "shape_pt_lon": "-97.803197", "shape_pt_sequence": "184", "shape_dist_traveled": "5.3653"}, {"shape_pt_lat": "30.232318", "shape_id": "39068", "shape_pt_lon": "-97.803644", "shape_pt_sequence": "185", "shape_dist_traveled": "5.4091"}, {"shape_pt_lat": "30.232297", "shape_id": "39068", "shape_pt_lon": "-97.803818", "shape_pt_sequence": "186", "shape_dist_traveled": "5.4263"}, {"shape_pt_lat": "30.232283", "shape_id": "39068", "shape_pt_lon": "-97.803991", "shape_pt_sequence": "187", "shape_dist_traveled": "5.4424"}, {"shape_pt_lat": "30.232279", "shape_id": "39068", "shape_pt_lon": "-97.804123", "shape_pt_sequence": "188", "shape_dist_traveled": "5.4554"}, {"shape_pt_lat": "30.232265", "shape_id": "39068", "shape_pt_lon": "-97.804432", "shape_pt_sequence": "189", "shape_dist_traveled": "5.4854"}, {"shape_pt_lat": "30.232263", "shape_id": "39068", "shape_pt_lon": "-97.804584", "shape_pt_sequence": "190", "shape_dist_traveled": "5.4994"}, {"shape_pt_lat": "30.232264", "shape_id": "39068", "shape_pt_lon": "-97.804740", "shape_pt_sequence": "191", "shape_dist_traveled": "5.5144"}, {"shape_pt_lat": "30.232272", "shape_id": "39068", "shape_pt_lon": "-97.804916", "shape_pt_sequence": "192", "shape_dist_traveled": "5.5315"}, {"shape_pt_lat": "30.232288", "shape_id": "39068", "shape_pt_lon": "-97.805230", "shape_pt_sequence": "193", "shape_dist_traveled": "5.5625"}, {"shape_pt_lat": "30.232313", "shape_id": "39068", "shape_pt_lon": "-97.805440", "shape_pt_sequence": "194", "shape_dist_traveled": "5.5827"}, {"shape_pt_lat": "30.232332", "shape_id": "39068", "shape_pt_lon": "-97.805593", "shape_pt_sequence": "195", "shape_dist_traveled": "5.5968"}, {"shape_pt_lat": "30.232391", "shape_id": "39068", "shape_pt_lon": "-97.805944", "shape_pt_sequence": "196", "shape_dist_traveled": "5.6315"}, {"shape_pt_lat": "30.232441", "shape_id": "39068", "shape_pt_lon": "-97.806175", "shape_pt_sequence": "197", "shape_dist_traveled": "5.6544"}, {"shape_pt_lat": "30.232487", "shape_id": "39068", "shape_pt_lon": "-97.806345", "shape_pt_sequence": "198", "shape_dist_traveled": "5.6721"}, {"shape_pt_lat": "30.232529", "shape_id": "39068", "shape_pt_lon": "-97.806505", "shape_pt_sequence": "199", "shape_dist_traveled": "5.6876"}, {"shape_pt_lat": "30.232575", "shape_id": "39068", "shape_pt_lon": "-97.806656", "shape_pt_sequence": "200", "shape_dist_traveled": "5.7034"}, {"shape_pt_lat": "30.232625", "shape_id": "39068", "shape_pt_lon": "-97.806813", "shape_pt_sequence": "201", "shape_dist_traveled": "5.7196"}, {"shape_pt_lat": "30.233316", "shape_id": "39068", "shape_pt_lon": "-97.808556", "shape_pt_sequence": "202", "shape_dist_traveled": "5.9035"}, {"shape_pt_lat": "30.233399", "shape_id": "39068", "shape_pt_lon": "-97.808778", "shape_pt_sequence": "203", "shape_dist_traveled": "5.9263"}, {"shape_pt_lat": "30.233491", "shape_id": "39068", "shape_pt_lon": "-97.808999", "shape_pt_sequence": "204", "shape_dist_traveled": "5.9505"}, {"shape_pt_lat": "30.233624", "shape_id": "39068", "shape_pt_lon": "-97.809356", "shape_pt_sequence": "205", "shape_dist_traveled": "5.9876"}, {"shape_pt_lat": "30.233704", "shape_id": "39068", "shape_pt_lon": "-97.809570", "shape_pt_sequence": "206", "shape_dist_traveled": "6.0096"}, {"shape_pt_lat": "30.233766", "shape_id": "39068", "shape_pt_lon": "-97.809763", "shape_pt_sequence": "207", "shape_dist_traveled": "6.0298"}, {"shape_pt_lat": "30.233811", "shape_id": "39068", "shape_pt_lon": "-97.809923", "shape_pt_sequence": "208", "shape_dist_traveled": "6.0456"}, {"shape_pt_lat": "30.233864", "shape_id": "39068", "shape_pt_lon": "-97.810118", "shape_pt_sequence": "209", "shape_dist_traveled": "6.0656"}, {"shape_pt_lat": "30.233910", "shape_id": "39068", "shape_pt_lon": "-97.810327", "shape_pt_sequence": "210", "shape_dist_traveled": "6.0862"}, {"shape_pt_lat": "30.233943", "shape_id": "39068", "shape_pt_lon": "-97.810510", "shape_pt_sequence": "211", "shape_dist_traveled": "6.1046"}, {"shape_pt_lat": "30.233969", "shape_id": "39068", "shape_pt_lon": "-97.810680", "shape_pt_sequence": "212", "shape_dist_traveled": "6.1209"}, {"shape_pt_lat": "30.233996", "shape_id": "39068", "shape_pt_lon": "-97.810878", "shape_pt_sequence": "213", "shape_dist_traveled": "6.1401"}, {"shape_pt_lat": "30.234012", "shape_id": "39068", "shape_pt_lon": "-97.811073", "shape_pt_sequence": "214", "shape_dist_traveled": "6.1592"}, {"shape_pt_lat": "30.234021", "shape_id": "39068", "shape_pt_lon": "-97.811188", "shape_pt_sequence": "215", "shape_dist_traveled": "6.1703"}, {"shape_pt_lat": "30.234025", "shape_id": "39068", "shape_pt_lon": "-97.811268", "shape_pt_sequence": "216", "shape_dist_traveled": "6.1783"}, {"shape_pt_lat": "30.234033", "shape_id": "39068", "shape_pt_lon": "-97.811400", "shape_pt_sequence": "217", "shape_dist_traveled": "6.1903"}, {"shape_pt_lat": "30.234039", "shape_id": "39068", "shape_pt_lon": "-97.811529", "shape_pt_sequence": "218", "shape_dist_traveled": "6.2034"}, {"shape_pt_lat": "30.234045", "shape_id": "39068", "shape_pt_lon": "-97.811706", "shape_pt_sequence": "219", "shape_dist_traveled": "6.2204"}, {"shape_pt_lat": "30.234040", "shape_id": "39068", "shape_pt_lon": "-97.811953", "shape_pt_sequence": "220", "shape_dist_traveled": "6.2434"}, {"shape_pt_lat": "30.234028", "shape_id": "39068", "shape_pt_lon": "-97.812175", "shape_pt_sequence": "221", "shape_dist_traveled": "6.2654"}, {"shape_pt_lat": "30.234005", "shape_id": "39068", "shape_pt_lon": "-97.812466", "shape_pt_sequence": "222", "shape_dist_traveled": "6.2935"}, {"shape_pt_lat": "30.233980", "shape_id": "39068", "shape_pt_lon": "-97.812791", "shape_pt_sequence": "223", "shape_dist_traveled": "6.3247"}, {"shape_pt_lat": "30.233896", "shape_id": "39068", "shape_pt_lon": "-97.813723", "shape_pt_sequence": "224", "shape_dist_traveled": "6.4151"}, {"shape_pt_lat": "30.233882", "shape_id": "39068", "shape_pt_lon": "-97.813933", "shape_pt_sequence": "225", "shape_dist_traveled": "6.4352"}, {"shape_pt_lat": "30.233866", "shape_id": "39068", "shape_pt_lon": "-97.814080", "shape_pt_sequence": "226", "shape_dist_traveled": "6.4492"}, {"shape_pt_lat": "30.233817", "shape_id": "39068", "shape_pt_lon": "-97.814603", "shape_pt_sequence": "227", "shape_dist_traveled": "6.4996"}, {"shape_pt_lat": "30.233611", "shape_id": "39068", "shape_pt_lon": "-97.816840", "shape_pt_sequence": "228", "shape_dist_traveled": "6.7157"}, {"shape_pt_lat": "30.233592", "shape_id": "39068", "shape_pt_lon": "-97.817039", "shape_pt_sequence": "229", "shape_dist_traveled": "6.7348"}, {"shape_pt_lat": "30.233560", "shape_id": "39068", "shape_pt_lon": "-97.817553", "shape_pt_sequence": "230", "shape_dist_traveled": "6.7850"}, {"shape_pt_lat": "30.233544", "shape_id": "39068", "shape_pt_lon": "-97.818060", "shape_pt_sequence": "231", "shape_dist_traveled": "6.8330"}, {"shape_pt_lat": "30.233548", "shape_id": "39068", "shape_pt_lon": "-97.818192", "shape_pt_sequence": "232", "shape_dist_traveled": "6.8460"}, {"shape_pt_lat": "30.233557", "shape_id": "39068", "shape_pt_lon": "-97.818355", "shape_pt_sequence": "233", "shape_dist_traveled": "6.8620"}, {"shape_pt_lat": "30.233613", "shape_id": "39068", "shape_pt_lon": "-97.818768", "shape_pt_sequence": "234", "shape_dist_traveled": "6.9025"}, {"shape_pt_lat": "30.233650", "shape_id": "39068", "shape_pt_lon": "-97.819021", "shape_pt_sequence": "235", "shape_dist_traveled": "6.9268"}, {"shape_pt_lat": "30.233697", "shape_id": "39068", "shape_pt_lon": "-97.819262", "shape_pt_sequence": "236", "shape_dist_traveled": "6.9506"}, {"shape_pt_lat": "30.233803", "shape_id": "39068", "shape_pt_lon": "-97.819710", "shape_pt_sequence": "237", "shape_dist_traveled": "6.9950"}, {"shape_pt_lat": "30.233882", "shape_id": "39068", "shape_pt_lon": "-97.819965", "shape_pt_sequence": "238", "shape_dist_traveled": "7.0215"}, {"shape_pt_lat": "30.234028", "shape_id": "39068", "shape_pt_lon": "-97.820321", "shape_pt_sequence": "239", "shape_dist_traveled": "7.0595"}, {"shape_pt_lat": "30.234146", "shape_id": "39068", "shape_pt_lon": "-97.820568", "shape_pt_sequence": "240", "shape_dist_traveled": "7.0860"}, {"shape_pt_lat": "30.234230", "shape_id": "39068", "shape_pt_lon": "-97.820727", "shape_pt_sequence": "241", "shape_dist_traveled": "7.1043"}, {"shape_pt_lat": "30.234445", "shape_id": "39068", "shape_pt_lon": "-97.821038", "shape_pt_sequence": "242", "shape_dist_traveled": "7.1427"}, {"shape_pt_lat": "30.234568", "shape_id": "39068", "shape_pt_lon": "-97.821212", "shape_pt_sequence": "243", "shape_dist_traveled": "7.1640"}, {"shape_pt_lat": "30.234787", "shape_id": "39068", "shape_pt_lon": "-97.821567", "shape_pt_sequence": "244", "shape_dist_traveled": "7.2056"}, {"shape_pt_lat": "30.234881", "shape_id": "39068", "shape_pt_lon": "-97.821689", "shape_pt_sequence": "245", "shape_dist_traveled": "7.2212"}, {"shape_pt_lat": "30.235074", "shape_id": "39068", "shape_pt_lon": "-97.821958", "shape_pt_sequence": "246", "shape_dist_traveled": "7.2553"}, {"shape_pt_lat": "30.235173", "shape_id": "39068", "shape_pt_lon": "-97.822110", "shape_pt_sequence": "247", "shape_dist_traveled": "7.2731"}, {"shape_pt_lat": "30.235289", "shape_id": "39068", "shape_pt_lon": "-97.822278", "shape_pt_sequence": "248", "shape_dist_traveled": "7.2945"}, {"shape_pt_lat": "30.235388", "shape_id": "39068", "shape_pt_lon": "-97.822443", "shape_pt_sequence": "249", "shape_dist_traveled": "7.3131"}, {"shape_pt_lat": "30.235483", "shape_id": "39068", "shape_pt_lon": "-97.822598", "shape_pt_sequence": "250", "shape_dist_traveled": "7.3311"}, {"shape_pt_lat": "30.235558", "shape_id": "39068", "shape_pt_lon": "-97.822732", "shape_pt_sequence": "251", "shape_dist_traveled": "7.3469"}, {"shape_pt_lat": "30.235627", "shape_id": "39068", "shape_pt_lon": "-97.822855", "shape_pt_sequence": "252", "shape_dist_traveled": "7.3608"}, {"shape_pt_lat": "30.235678", "shape_id": "39068", "shape_pt_lon": "-97.822956", "shape_pt_sequence": "253", "shape_dist_traveled": "7.3725"}, {"shape_pt_lat": "30.235733", "shape_id": "39068", "shape_pt_lon": "-97.823057", "shape_pt_sequence": "254", "shape_dist_traveled": "7.3833"}, {"shape_pt_lat": "30.235794", "shape_id": "39068", "shape_pt_lon": "-97.823205", "shape_pt_sequence": "255", "shape_dist_traveled": "7.3999"}, {"shape_pt_lat": "30.235916", "shape_id": "39068", "shape_pt_lon": "-97.823494", "shape_pt_sequence": "256", "shape_dist_traveled": "7.4303"}, {"shape_pt_lat": "30.236005", "shape_id": "39068", "shape_pt_lon": "-97.823704", "shape_pt_sequence": "257", "shape_dist_traveled": "7.4535"}, {"shape_pt_lat": "30.236087", "shape_id": "39068", "shape_pt_lon": "-97.823894", "shape_pt_sequence": "258", "shape_dist_traveled": "7.4737"}, {"shape_pt_lat": "30.236135", "shape_id": "39068", "shape_pt_lon": "-97.824023", "shape_pt_sequence": "259", "shape_dist_traveled": "7.4867"}, {"shape_pt_lat": "30.236160", "shape_id": "39068", "shape_pt_lon": "-97.824091", "shape_pt_sequence": "260", "shape_dist_traveled": "7.4943"}, {"shape_pt_lat": "30.236172", "shape_id": "39068", "shape_pt_lon": "-97.824143", "shape_pt_sequence": "261", "shape_dist_traveled": "7.4994"}, {"shape_pt_lat": "30.236213", "shape_id": "39068", "shape_pt_lon": "-97.824262", "shape_pt_sequence": "262", "shape_dist_traveled": "7.5115"}, {"shape_pt_lat": "30.236338", "shape_id": "39068", "shape_pt_lon": "-97.824648", "shape_pt_sequence": "263", "shape_dist_traveled": "7.5510"}, {"shape_pt_lat": "30.236394", "shape_id": "39068", "shape_pt_lon": "-97.824831", "shape_pt_sequence": "264", "shape_dist_traveled": "7.5700"}, {"shape_pt_lat": "30.236451", "shape_id": "39068", "shape_pt_lon": "-97.825019", "shape_pt_sequence": "265", "shape_dist_traveled": "7.5890"}, {"shape_pt_lat": "30.236613", "shape_id": "39068", "shape_pt_lon": "-97.825507", "shape_pt_sequence": "266", "shape_dist_traveled": "7.6393"}, {"shape_pt_lat": "30.236683", "shape_id": "39068", "shape_pt_lon": "-97.825741", "shape_pt_sequence": "267", "shape_dist_traveled": "7.6627"}, {"shape_pt_lat": "30.236700", "shape_id": "39068", "shape_pt_lon": "-97.825795", "shape_pt_sequence": "268", "shape_dist_traveled": "7.6681"}, {"shape_pt_lat": "30.236736", "shape_id": "39068", "shape_pt_lon": "-97.825939", "shape_pt_sequence": "269", "shape_dist_traveled": "7.6827"}, {"shape_pt_lat": "30.236796", "shape_id": "39068", "shape_pt_lon": "-97.826196", "shape_pt_sequence": "270", "shape_dist_traveled": "7.7086"}, {"shape_pt_lat": "30.236825", "shape_id": "39068", "shape_pt_lon": "-97.826320", "shape_pt_sequence": "271", "shape_dist_traveled": "7.7210"}, {"shape_pt_lat": "30.236851", "shape_id": "39068", "shape_pt_lon": "-97.826455", "shape_pt_sequence": "272", "shape_dist_traveled": "7.7343"}, {"shape_pt_lat": "30.236898", "shape_id": "39068", "shape_pt_lon": "-97.826645", "shape_pt_sequence": "273", "shape_dist_traveled": "7.7530"}, {"shape_pt_lat": "30.236935", "shape_id": "39068", "shape_pt_lon": "-97.826890", "shape_pt_sequence": "274", "shape_dist_traveled": "7.7773"}, {"shape_pt_lat": "30.236966", "shape_id": "39068", "shape_pt_lon": "-97.827203", "shape_pt_sequence": "275", "shape_dist_traveled": "7.8076"}, {"shape_pt_lat": "30.236989", "shape_id": "39068", "shape_pt_lon": "-97.827552", "shape_pt_sequence": "276", "shape_dist_traveled": "7.8407"}, {"shape_pt_lat": "30.237002", "shape_id": "39068", "shape_pt_lon": "-97.827962", "shape_pt_sequence": "277", "shape_dist_traveled": "7.8807"}, {"shape_pt_lat": "30.237001", "shape_id": "39068", "shape_pt_lon": "-97.828516", "shape_pt_sequence": "278", "shape_dist_traveled": "7.9337"}, {"shape_pt_lat": "30.236998", "shape_id": "39068", "shape_pt_lon": "-97.829217", "shape_pt_sequence": "279", "shape_dist_traveled": "8.0007"}, {"shape_pt_lat": "30.236985", "shape_id": "39068", "shape_pt_lon": "-97.829615", "shape_pt_sequence": "280", "shape_dist_traveled": "8.0388"}, {"shape_pt_lat": "30.236974", "shape_id": "39068", "shape_pt_lon": "-97.829795", "shape_pt_sequence": "281", "shape_dist_traveled": "8.0568"}, {"shape_pt_lat": "30.236991", "shape_id": "39068", "shape_pt_lon": "-97.831031", "shape_pt_sequence": "282", "shape_dist_traveled": "8.1758"}, {"shape_pt_lat": "30.236979", "shape_id": "39068", "shape_pt_lon": "-97.831514", "shape_pt_sequence": "283", "shape_dist_traveled": "8.2218"}, {"shape_pt_lat": "30.236987", "shape_id": "39068", "shape_pt_lon": "-97.832480", "shape_pt_sequence": "284", "shape_dist_traveled": "8.3148"}, {"shape_pt_lat": "30.236984", "shape_id": "39068", "shape_pt_lon": "-97.832735", "shape_pt_sequence": "285", "shape_dist_traveled": "8.3388"}, {"shape_pt_lat": "30.236980", "shape_id": "39068", "shape_pt_lon": "-97.832939", "shape_pt_sequence": "286", "shape_dist_traveled": "8.3589"}, {"shape_pt_lat": "30.236967", "shape_id": "39068", "shape_pt_lon": "-97.833315", "shape_pt_sequence": "287", "shape_dist_traveled": "8.3949"}, {"shape_pt_lat": "30.236964", "shape_id": "39068", "shape_pt_lon": "-97.833735", "shape_pt_sequence": "288", "shape_dist_traveled": "8.4349"}, {"shape_pt_lat": "30.236969", "shape_id": "39068", "shape_pt_lon": "-97.834076", "shape_pt_sequence": "289", "shape_dist_traveled": "8.4679"}, {"shape_pt_lat": "30.236992", "shape_id": "39068", "shape_pt_lon": "-97.838351", "shape_pt_sequence": "290", "shape_dist_traveled": "8.8789"}, {"shape_pt_lat": "30.236995", "shape_id": "39068", "shape_pt_lon": "-97.838515", "shape_pt_sequence": "291", "shape_dist_traveled": "8.8949"}, {"shape_pt_lat": "30.236993", "shape_id": "39068", "shape_pt_lon": "-97.838663", "shape_pt_sequence": "292", "shape_dist_traveled": "8.9090"}, {"shape_pt_lat": "30.237024", "shape_id": "39068", "shape_pt_lon": "-97.839904", "shape_pt_sequence": "293", "shape_dist_traveled": "9.0280"}, {"shape_pt_lat": "30.237030", "shape_id": "39068", "shape_pt_lon": "-97.841207", "shape_pt_sequence": "294", "shape_dist_traveled": "9.1540"}, {"shape_pt_lat": "30.237032", "shape_id": "39068", "shape_pt_lon": "-97.841415", "shape_pt_sequence": "295", "shape_dist_traveled": "9.1740"}, {"shape_pt_lat": "30.237031", "shape_id": "39068", "shape_pt_lon": "-97.841758", "shape_pt_sequence": "296", "shape_dist_traveled": "9.2060"}, {"shape_pt_lat": "30.237024", "shape_id": "39068", "shape_pt_lon": "-97.842177", "shape_pt_sequence": "297", "shape_dist_traveled": "9.2471"}, {"shape_pt_lat": "30.237012", "shape_id": "39068", "shape_pt_lon": "-97.842526", "shape_pt_sequence": "298", "shape_dist_traveled": "9.2801"}, {"shape_pt_lat": "30.237003", "shape_id": "39068", "shape_pt_lon": "-97.842684", "shape_pt_sequence": "299", "shape_dist_traveled": "9.2951"}, {"shape_pt_lat": "30.236997", "shape_id": "39068", "shape_pt_lon": "-97.842782", "shape_pt_sequence": "300", "shape_dist_traveled": "9.3051"}, {"shape_pt_lat": "30.236983", "shape_id": "39068", "shape_pt_lon": "-97.843001", "shape_pt_sequence": "301", "shape_dist_traveled": "9.3262"}, {"shape_pt_lat": "30.236959", "shape_id": "39068", "shape_pt_lon": "-97.843238", "shape_pt_sequence": "302", "shape_dist_traveled": "9.3494"}, {"shape_pt_lat": "30.236873", "shape_id": "39068", "shape_pt_lon": "-97.843942", "shape_pt_sequence": "303", "shape_dist_traveled": "9.4170"}, {"shape_pt_lat": "30.236634", "shape_id": "39068", "shape_pt_lon": "-97.845877", "shape_pt_sequence": "304", "shape_dist_traveled": "9.6048"}, {"shape_pt_lat": "30.236346", "shape_id": "39068", "shape_pt_lon": "-97.847685", "shape_pt_sequence": "305", "shape_dist_traveled": "9.7817"}, {"shape_pt_lat": "30.235848", "shape_id": "39068", "shape_pt_lon": "-97.850317", "shape_pt_sequence": "306", "shape_dist_traveled": "10.0406"}, {"shape_pt_lat": "30.235808", "shape_id": "39068", "shape_pt_lon": "-97.850540", "shape_pt_sequence": "307", "shape_dist_traveled": "10.0630"}, {"shape_pt_lat": "30.235779", "shape_id": "39068", "shape_pt_lon": "-97.850753", "shape_pt_sequence": "308", "shape_dist_traveled": "10.0832"}, {"shape_pt_lat": "30.235732", "shape_id": "39068", "shape_pt_lon": "-97.851107", "shape_pt_sequence": "309", "shape_dist_traveled": "10.1177"}, {"shape_pt_lat": "30.235727", "shape_id": "39068", "shape_pt_lon": "-97.851151", "shape_pt_sequence": "310", "shape_dist_traveled": "10.1217"}, {"shape_pt_lat": "30.235684", "shape_id": "39068", "shape_pt_lon": "-97.851565", "shape_pt_sequence": "311", "shape_dist_traveled": "10.1621"}, {"shape_pt_lat": "30.235674", "shape_id": "39068", "shape_pt_lon": "-97.852129", "shape_pt_sequence": "312", "shape_dist_traveled": "10.2161"}, {"shape_pt_lat": "30.235670", "shape_id": "39068", "shape_pt_lon": "-97.852231", "shape_pt_sequence": "313", "shape_dist_traveled": "10.2261"}, {"shape_pt_lat": "30.235640", "shape_id": "39068", "shape_pt_lon": "-97.853004", "shape_pt_sequence": "314", "shape_dist_traveled": "10.3011"}, {"shape_pt_lat": "30.235621", "shape_id": "39068", "shape_pt_lon": "-97.854018", "shape_pt_sequence": "315", "shape_dist_traveled": "10.3981"}, {"shape_pt_lat": "30.235595", "shape_id": "39068", "shape_pt_lon": "-97.855533", "shape_pt_sequence": "316", "shape_dist_traveled": "10.5442"}, {"shape_pt_lat": "30.235536", "shape_id": "39068", "shape_pt_lon": "-97.856694", "shape_pt_sequence": "317", "shape_dist_traveled": "10.6553"}, {"shape_pt_lat": "30.235484", "shape_id": "39068", "shape_pt_lon": "-97.857052", "shape_pt_sequence": "318", "shape_dist_traveled": "10.6908"}, {"shape_pt_lat": "30.235483", "shape_id": "39068", "shape_pt_lon": "-97.857245", "shape_pt_sequence": "319", "shape_dist_traveled": "10.7088"}, {"shape_pt_lat": "30.235478", "shape_id": "39068", "shape_pt_lon": "-97.857558", "shape_pt_sequence": "320", "shape_dist_traveled": "10.7389"}, {"shape_pt_lat": "30.235476", "shape_id": "39068", "shape_pt_lon": "-97.857839", "shape_pt_sequence": "321", "shape_dist_traveled": "10.7659"}, {"shape_pt_lat": "30.235469", "shape_id": "39068", "shape_pt_lon": "-97.858198", "shape_pt_sequence": "322", "shape_dist_traveled": "10.8009"}, {"shape_pt_lat": "30.235471", "shape_id": "39068", "shape_pt_lon": "-97.859212", "shape_pt_sequence": "323", "shape_dist_traveled": "10.8979"}, {"shape_pt_lat": "30.235461", "shape_id": "39068", "shape_pt_lon": "-97.859551", "shape_pt_sequence": "324", "shape_dist_traveled": "10.9309"}, {"shape_pt_lat": "30.235445", "shape_id": "39068", "shape_pt_lon": "-97.859736", "shape_pt_sequence": "325", "shape_dist_traveled": "10.9490"}, {"shape_pt_lat": "30.235429", "shape_id": "39068", "shape_pt_lon": "-97.859861", "shape_pt_sequence": "326", "shape_dist_traveled": "10.9612"}, {"shape_pt_lat": "30.235423", "shape_id": "39068", "shape_pt_lon": "-97.859877", "shape_pt_sequence": "327", "shape_dist_traveled": "10.9622"}, {"shape_pt_lat": "30.235376", "shape_id": "39068", "shape_pt_lon": "-97.859936", "shape_pt_sequence": "328", "shape_dist_traveled": "10.9707"}, {"shape_pt_lat": "30.235365", "shape_id": "39068", "shape_pt_lon": "-97.859996", "shape_pt_sequence": "329", "shape_dist_traveled": "10.9767"}, {"shape_pt_lat": "30.235358", "shape_id": "39068", "shape_pt_lon": "-97.860047", "shape_pt_sequence": "330", "shape_dist_traveled": "10.9818"}, {"shape_pt_lat": "30.235300", "shape_id": "39068", "shape_pt_lon": "-97.860395", "shape_pt_sequence": "331", "shape_dist_traveled": "11.0154"}, {"shape_pt_lat": "30.235281", "shape_id": "39068", "shape_pt_lon": "-97.860500", "shape_pt_sequence": "332", "shape_dist_traveled": "11.0256"}, {"shape_pt_lat": "30.235255", "shape_id": "39068", "shape_pt_lon": "-97.860650", "shape_pt_sequence": "333", "shape_dist_traveled": "11.0409"}, {"shape_pt_lat": "30.235179", "shape_id": "39068", "shape_pt_lon": "-97.861034", "shape_pt_sequence": "334", "shape_dist_traveled": "11.0778"}, {"shape_pt_lat": "30.235133", "shape_id": "39068", "shape_pt_lon": "-97.861252", "shape_pt_sequence": "335", "shape_dist_traveled": "11.0993"}, {"shape_pt_lat": "30.235079", "shape_id": "39068", "shape_pt_lon": "-97.861475", "shape_pt_sequence": "336", "shape_dist_traveled": "11.1221"}, {"shape_pt_lat": "30.235070", "shape_id": "39068", "shape_pt_lon": "-97.861507", "shape_pt_sequence": "337", "shape_dist_traveled": "11.1253"}, {"shape_pt_lat": "30.234999", "shape_id": "39068", "shape_pt_lon": "-97.861700", "shape_pt_sequence": "338", "shape_dist_traveled": "11.1450"}, {"shape_pt_lat": "30.234928", "shape_id": "39068", "shape_pt_lon": "-97.861869", "shape_pt_sequence": "339", "shape_dist_traveled": "11.1638"}, {"shape_pt_lat": "30.234850", "shape_id": "39068", "shape_pt_lon": "-97.862066", "shape_pt_sequence": "340", "shape_dist_traveled": "11.1848"}, {"shape_pt_lat": "30.234769", "shape_id": "39068", "shape_pt_lon": "-97.862242", "shape_pt_sequence": "341", "shape_dist_traveled": "11.2041"}, {"shape_pt_lat": "30.234663", "shape_id": "39068", "shape_pt_lon": "-97.862473", "shape_pt_sequence": "342", "shape_dist_traveled": "11.2287"}, {"shape_pt_lat": "30.234670", "shape_id": "39068", "shape_pt_lon": "-97.862587", "shape_pt_sequence": "343", "shape_dist_traveled": "11.2397"}, {"shape_pt_lat": "30.234596", "shape_id": "39068", "shape_pt_lon": "-97.862766", "shape_pt_sequence": "344", "shape_dist_traveled": "11.2589"}, {"shape_pt_lat": "30.234535", "shape_id": "39068", "shape_pt_lon": "-97.862912", "shape_pt_sequence": "345", "shape_dist_traveled": "11.2742"}, {"shape_pt_lat": "30.234510", "shape_id": "39068", "shape_pt_lon": "-97.862983", "shape_pt_sequence": "346", "shape_dist_traveled": "11.2818"}, {"shape_pt_lat": "30.234471", "shape_id": "39068", "shape_pt_lon": "-97.863091", "shape_pt_sequence": "347", "shape_dist_traveled": "11.2925"}, {"shape_pt_lat": "30.234403", "shape_id": "39068", "shape_pt_lon": "-97.863270", "shape_pt_sequence": "348", "shape_dist_traveled": "11.3122"}, {"shape_pt_lat": "30.234387", "shape_id": "39068", "shape_pt_lon": "-97.863328", "shape_pt_sequence": "349", "shape_dist_traveled": "11.3176"}, {"shape_pt_lat": "30.234352", "shape_id": "39068", "shape_pt_lon": "-97.863446", "shape_pt_sequence": "350", "shape_dist_traveled": "11.3293"}, {"shape_pt_lat": "30.234247", "shape_id": "39068", "shape_pt_lon": "-97.863799", "shape_pt_sequence": "351", "shape_dist_traveled": "11.3651"}, {"shape_pt_lat": "30.234141", "shape_id": "39068", "shape_pt_lon": "-97.864141", "shape_pt_sequence": "352", "shape_dist_traveled": "11.4002"}, {"shape_pt_lat": "30.234071", "shape_id": "39068", "shape_pt_lon": "-97.864401", "shape_pt_sequence": "353", "shape_dist_traveled": "11.4264"}, {"shape_pt_lat": "30.234021", "shape_id": "39068", "shape_pt_lon": "-97.864571", "shape_pt_sequence": "354", "shape_dist_traveled": "11.4442"}, {"shape_pt_lat": "30.233988", "shape_id": "39068", "shape_pt_lon": "-97.864710", "shape_pt_sequence": "355", "shape_dist_traveled": "11.4578"}, {"shape_pt_lat": "30.233973", "shape_id": "39068", "shape_pt_lon": "-97.864795", "shape_pt_sequence": "356", "shape_dist_traveled": "11.4658"}, {"shape_pt_lat": "30.233958", "shape_id": "39068", "shape_pt_lon": "-97.864877", "shape_pt_sequence": "357", "shape_dist_traveled": "11.4741"}, {"shape_pt_lat": "30.233933", "shape_id": "39068", "shape_pt_lon": "-97.865091", "shape_pt_sequence": "358", "shape_dist_traveled": "11.4953"}, {"shape_pt_lat": "30.233923", "shape_id": "39068", "shape_pt_lon": "-97.865223", "shape_pt_sequence": "359", "shape_dist_traveled": "11.5073"}, {"shape_pt_lat": "30.233916", "shape_id": "39068", "shape_pt_lon": "-97.865337", "shape_pt_sequence": "360", "shape_dist_traveled": "11.5184"}, {"shape_pt_lat": "30.233916", "shape_id": "39068", "shape_pt_lon": "-97.865440", "shape_pt_sequence": "361", "shape_dist_traveled": "11.5284"}, {"shape_pt_lat": "30.233916", "shape_id": "39068", "shape_pt_lon": "-97.865560", "shape_pt_sequence": "362", "shape_dist_traveled": "11.5404"}, {"shape_pt_lat": "30.233920", "shape_id": "39068", "shape_pt_lon": "-97.865665", "shape_pt_sequence": "363", "shape_dist_traveled": "11.5504"}, {"shape_pt_lat": "30.233926", "shape_id": "39068", "shape_pt_lon": "-97.865769", "shape_pt_sequence": "364", "shape_dist_traveled": "11.5605"}, {"shape_pt_lat": "30.233931", "shape_id": "39068", "shape_pt_lon": "-97.865822", "shape_pt_sequence": "365", "shape_dist_traveled": "11.5655"}, {"shape_pt_lat": "30.233938", "shape_id": "39068", "shape_pt_lon": "-97.865895", "shape_pt_sequence": "366", "shape_dist_traveled": "11.5725"}, {"shape_pt_lat": "30.233973", "shape_id": "39068", "shape_pt_lon": "-97.866082", "shape_pt_sequence": "367", "shape_dist_traveled": "11.5910"}, {"shape_pt_lat": "30.233979", "shape_id": "39068", "shape_pt_lon": "-97.866209", "shape_pt_sequence": "368", "shape_dist_traveled": "11.6030"}, {"shape_pt_lat": "30.234005", "shape_id": "39068", "shape_pt_lon": "-97.866560", "shape_pt_sequence": "369", "shape_dist_traveled": "11.6371"}, {"shape_pt_lat": "30.234021", "shape_id": "39068", "shape_pt_lon": "-97.866702", "shape_pt_sequence": "370", "shape_dist_traveled": "11.6503"}, {"shape_pt_lat": "30.233993", "shape_id": "39068", "shape_pt_lon": "-97.866798", "shape_pt_sequence": "371", "shape_dist_traveled": "11.6607"}, {"shape_pt_lat": "30.234008", "shape_id": "39068", "shape_pt_lon": "-97.866926", "shape_pt_sequence": "372", "shape_dist_traveled": "11.6729"}, {"shape_pt_lat": "30.234039", "shape_id": "39068", "shape_pt_lon": "-97.867197", "shape_pt_sequence": "373", "shape_dist_traveled": "11.6990"}, {"shape_pt_lat": "30.234055", "shape_id": "39068", "shape_pt_lon": "-97.867411", "shape_pt_sequence": "374", "shape_dist_traveled": "11.7201"}, {"shape_pt_lat": "30.234065", "shape_id": "39068", "shape_pt_lon": "-97.867661", "shape_pt_sequence": "375", "shape_dist_traveled": "11.7442"}, {"shape_pt_lat": "30.234060", "shape_id": "39068", "shape_pt_lon": "-97.867941", "shape_pt_sequence": "376", "shape_dist_traveled": "11.7712"}, {"shape_pt_lat": "30.234052", "shape_id": "39068", "shape_pt_lon": "-97.868391", "shape_pt_sequence": "377", "shape_dist_traveled": "11.8142"}, {"shape_pt_lat": "30.234040", "shape_id": "39068", "shape_pt_lon": "-97.868906", "shape_pt_sequence": "378", "shape_dist_traveled": "11.8632"}, {"shape_pt_lat": "30.233985", "shape_id": "39068", "shape_pt_lon": "-97.871245", "shape_pt_sequence": "379", "shape_dist_traveled": "12.0883"}, {"shape_pt_lat": "30.233961", "shape_id": "39068", "shape_pt_lon": "-97.871690", "shape_pt_sequence": "380", "shape_dist_traveled": "12.1313"}, {"shape_pt_lat": "30.233925", "shape_id": "39068", "shape_pt_lon": "-97.872185", "shape_pt_sequence": "381", "shape_dist_traveled": "12.1785"}, {"shape_pt_lat": "30.233968", "shape_id": "39068", "shape_pt_lon": "-97.872317", "shape_pt_sequence": "382", "shape_dist_traveled": "12.1921"}, {"shape_pt_lat": "30.233942", "shape_id": "39068", "shape_pt_lon": "-97.872565", "shape_pt_sequence": "383", "shape_dist_traveled": "12.2162"}, {"shape_pt_lat": "30.233971", "shape_id": "39068", "shape_pt_lon": "-97.872830", "shape_pt_sequence": "384", "shape_dist_traveled": "12.2413"}, {"shape_pt_lat": "30.233974", "shape_id": "39068", "shape_pt_lon": "-97.872990", "shape_pt_sequence": "385", "shape_dist_traveled": "12.2573"}, {"shape_pt_lat": "30.233985", "shape_id": "39068", "shape_pt_lon": "-97.873176", "shape_pt_sequence": "386", "shape_dist_traveled": "12.2754"}, {"shape_pt_lat": "30.234007", "shape_id": "39068", "shape_pt_lon": "-97.873471", "shape_pt_sequence": "387", "shape_dist_traveled": "12.3035"}, {"shape_pt_lat": "30.234067", "shape_id": "39068", "shape_pt_lon": "-97.873943", "shape_pt_sequence": "388", "shape_dist_traveled": "12.3491"}, {"shape_pt_lat": "30.234119", "shape_id": "39068", "shape_pt_lon": "-97.874194", "shape_pt_sequence": "389", "shape_dist_traveled": "12.3738"}, {"shape_pt_lat": "30.234185", "shape_id": "39068", "shape_pt_lon": "-97.874461", "shape_pt_sequence": "390", "shape_dist_traveled": "12.4007"}, {"shape_pt_lat": "30.234344", "shape_id": "39068", "shape_pt_lon": "-97.874976", "shape_pt_sequence": "391", "shape_dist_traveled": "12.4539"}, {"shape_pt_lat": "30.234470", "shape_id": "39068", "shape_pt_lon": "-97.875249", "shape_pt_sequence": "392", "shape_dist_traveled": "12.4834"}, {"shape_pt_lat": "30.234646", "shape_id": "39068", "shape_pt_lon": "-97.875568", "shape_pt_sequence": "393", "shape_dist_traveled": "12.5189"}, {"shape_pt_lat": "30.234691", "shape_id": "39068", "shape_pt_lon": "-97.875665", "shape_pt_sequence": "394", "shape_dist_traveled": "12.5301"}, {"shape_pt_lat": "30.234736", "shape_id": "39068", "shape_pt_lon": "-97.875762", "shape_pt_sequence": "395", "shape_dist_traveled": "12.5404"}, {"shape_pt_lat": "30.234791", "shape_id": "39068", "shape_pt_lon": "-97.875876", "shape_pt_sequence": "396", "shape_dist_traveled": "12.5529"}, {"shape_pt_lat": "30.234885", "shape_id": "39068", "shape_pt_lon": "-97.876028", "shape_pt_sequence": "397", "shape_dist_traveled": "12.5715"}, {"shape_pt_lat": "30.234953", "shape_id": "39068", "shape_pt_lon": "-97.876142", "shape_pt_sequence": "398", "shape_dist_traveled": "12.5846"}, {"shape_pt_lat": "30.234957", "shape_id": "39068", "shape_pt_lon": "-97.876223", "shape_pt_sequence": "399", "shape_dist_traveled": "12.5916"}, {"shape_pt_lat": "30.235017", "shape_id": "39068", "shape_pt_lon": "-97.876320", "shape_pt_sequence": "400", "shape_dist_traveled": "12.6038"}, {"shape_pt_lat": "30.235067", "shape_id": "39068", "shape_pt_lon": "-97.876386", "shape_pt_sequence": "401", "shape_dist_traveled": "12.6116"}, {"shape_pt_lat": "30.235177", "shape_id": "39068", "shape_pt_lon": "-97.876537", "shape_pt_sequence": "402", "shape_dist_traveled": "12.6301"}, {"shape_pt_lat": "30.234853", "shape_id": "39068", "shape_pt_lon": "-97.876841", "shape_pt_sequence": "403", "shape_dist_traveled": "12.6762"}, {"shape_pt_lat": "30.235079", "shape_id": "39068", "shape_pt_lon": "-97.877155", "shape_pt_sequence": "404", "shape_dist_traveled": "12.7152"}, {"shape_pt_lat": "30.235177", "shape_id": "39068", "shape_pt_lon": "-97.877185", "shape_pt_sequence": "405", "shape_dist_traveled": "12.7266"}, {"shape_pt_lat": "30.235252", "shape_id": "39068", "shape_pt_lon": "-97.877137", "shape_pt_sequence": "406", "shape_dist_traveled": "12.7361"}, {"shape_pt_lat": "30.235373", "shape_id": "39068", "shape_pt_lon": "-97.877164", "shape_pt_sequence": "407", "shape_dist_traveled": "12.7494"}, {"shape_pt_lat": "30.235435", "shape_id": "39068", "shape_pt_lon": "-97.877185", "shape_pt_sequence": "408", "shape_dist_traveled": "12.7567"}, {"shape_pt_lat": "30.235571", "shape_id": "39068", "shape_pt_lon": "-97.877050", "shape_pt_sequence": "409", "shape_dist_traveled": "12.7765"}, {"shape_pt_lat": "30.235393", "shape_id": "39068", "shape_pt_lon": "-97.876824", "shape_pt_sequence": "410", "shape_dist_traveled": "12.8063"}, {"shape_pt_lat": "30.235207", "shape_id": "39068", "shape_pt_lon": "-97.876575", "shape_pt_sequence": "411", "shape_dist_traveled": "12.8375"}, {"shape_pt_lat": "30.235177", "shape_id": "39068", "shape_pt_lon": "-97.876537", "shape_pt_sequence": "412", "shape_dist_traveled": "12.8432"}, {"shape_pt_lat": "30.235067", "shape_id": "39068", "shape_pt_lon": "-97.876386", "shape_pt_sequence": "413", "shape_dist_traveled": "12.8616"}, {"shape_pt_lat": "30.235017", "shape_id": "39068", "shape_pt_lon": "-97.876320", "shape_pt_sequence": "414", "shape_dist_traveled": "12.8694"}, {"shape_pt_lat": "30.234957", "shape_id": "39068", "shape_pt_lon": "-97.876223", "shape_pt_sequence": "415", "shape_dist_traveled": "12.8816"}, {"shape_pt_lat": "30.234900", "shape_id": "39068", "shape_pt_lon": "-97.876187", "shape_pt_sequence": "416", "shape_dist_traveled": "12.8883"}, {"shape_pt_lat": "30.234733", "shape_id": "39068", "shape_pt_lon": "-97.875923", "shape_pt_sequence": "417", "shape_dist_traveled": "12.9197"}, {"shape_pt_lat": "30.234604", "shape_id": "39068", "shape_pt_lon": "-97.875723", "shape_pt_sequence": "418", "shape_dist_traveled": "12.9441"}, {"shape_pt_lat": "30.234532", "shape_id": "39068", "shape_pt_lon": "-97.875607", "shape_pt_sequence": "419", "shape_dist_traveled": "12.9577"}, {"shape_pt_lat": "30.234445", "shape_id": "39068", "shape_pt_lon": "-97.875492", "shape_pt_sequence": "420", "shape_dist_traveled": "12.9726"}, {"shape_pt_lat": "30.234419", "shape_id": "39068", "shape_pt_lon": "-97.875464", "shape_pt_sequence": "421", "shape_dist_traveled": "12.9769"}, {"shape_pt_lat": "30.234390", "shape_id": "39068", "shape_pt_lon": "-97.875430", "shape_pt_sequence": "422", "shape_dist_traveled": "12.9811"}, {"shape_pt_lat": "30.234208", "shape_id": "39068", "shape_pt_lon": "-97.875262", "shape_pt_sequence": "423", "shape_dist_traveled": "13.0067"}, {"shape_pt_lat": "30.234084", "shape_id": "39068", "shape_pt_lon": "-97.875168", "shape_pt_sequence": "424", "shape_dist_traveled": "13.0234"}, {"shape_pt_lat": "30.233828", "shape_id": "39068", "shape_pt_lon": "-97.875017", "shape_pt_sequence": "425", "shape_dist_traveled": "13.0556"}, {"shape_pt_lat": "30.233750", "shape_id": "39068", "shape_pt_lon": "-97.875002", "shape_pt_sequence": "426", "shape_dist_traveled": "13.0638"}, {"shape_pt_lat": "30.233663", "shape_id": "39068", "shape_pt_lon": "-97.875005", "shape_pt_sequence": "427", "shape_dist_traveled": "13.0739"}, {"shape_pt_lat": "30.233573", "shape_id": "39068", "shape_pt_lon": "-97.875016", "shape_pt_sequence": "428", "shape_dist_traveled": "13.0839"}, {"shape_pt_lat": "30.233493", "shape_id": "39068", "shape_pt_lon": "-97.875045", "shape_pt_sequence": "429", "shape_dist_traveled": "13.0931"}, {"shape_pt_lat": "30.233442", "shape_id": "39068", "shape_pt_lon": "-97.875085", "shape_pt_sequence": "430", "shape_dist_traveled": "13.0995"}, {"shape_pt_lat": "30.233403", "shape_id": "39068", "shape_pt_lon": "-97.875125", "shape_pt_sequence": "431", "shape_dist_traveled": "13.1059"}, {"shape_pt_lat": "30.233366", "shape_id": "39068", "shape_pt_lon": "-97.875190", "shape_pt_sequence": "432", "shape_dist_traveled": "13.1131"}, {"shape_pt_lat": "30.233269", "shape_id": "39068", "shape_pt_lon": "-97.875414", "shape_pt_sequence": "433", "shape_dist_traveled": "13.1377"}, {"shape_pt_lat": "30.233160", "shape_id": "39068", "shape_pt_lon": "-97.875667", "shape_pt_sequence": "434", "shape_dist_traveled": "13.1646"}, {"shape_pt_lat": "30.233095", "shape_id": "39068", "shape_pt_lon": "-97.875805", "shape_pt_sequence": "435", "shape_dist_traveled": "13.1802"}, {"shape_pt_lat": "30.233048", "shape_id": "39068", "shape_pt_lon": "-97.875870", "shape_pt_sequence": "436", "shape_dist_traveled": "13.1880"}, {"shape_pt_lat": "30.232998", "shape_id": "39068", "shape_pt_lon": "-97.875928", "shape_pt_sequence": "437", "shape_dist_traveled": "13.1958"}, {"shape_pt_lat": "30.232943", "shape_id": "39068", "shape_pt_lon": "-97.875975", "shape_pt_sequence": "438", "shape_dist_traveled": "13.2037"}, {"shape_pt_lat": "30.232856", "shape_id": "39068", "shape_pt_lon": "-97.876036", "shape_pt_sequence": "439", "shape_dist_traveled": "13.2145"}, {"shape_pt_lat": "30.232763", "shape_id": "39068", "shape_pt_lon": "-97.876123", "shape_pt_sequence": "440", "shape_dist_traveled": "13.2281"}, {"shape_pt_lat": "30.232667", "shape_id": "39068", "shape_pt_lon": "-97.876289", "shape_pt_sequence": "441", "shape_dist_traveled": "13.2469"}, {"shape_pt_lat": "30.232522", "shape_id": "39068", "shape_pt_lon": "-97.876538", "shape_pt_sequence": "442", "shape_dist_traveled": "13.2758"}, {"shape_pt_lat": "30.232169", "shape_id": "39068", "shape_pt_lon": "-97.877057", "shape_pt_sequence": "443", "shape_dist_traveled": "13.3392"}, {"shape_pt_lat": "30.232091", "shape_id": "39068", "shape_pt_lon": "-97.877170", "shape_pt_sequence": "444", "shape_dist_traveled": "13.3534"}, {"shape_pt_lat": "30.231985", "shape_id": "39068", "shape_pt_lon": "-97.877232", "shape_pt_sequence": "445", "shape_dist_traveled": "13.3668"}, {"shape_pt_lat": "30.231309", "shape_id": "39068", "shape_pt_lon": "-97.878414", "shape_pt_sequence": "446", "shape_dist_traveled": "13.5033"}, {"shape_pt_lat": "30.231002", "shape_id": "39068", "shape_pt_lon": "-97.878922", "shape_pt_sequence": "447", "shape_dist_traveled": "13.5629"}, {"shape_pt_lat": "30.230761", "shape_id": "39068", "shape_pt_lon": "-97.879324", "shape_pt_sequence": "448", "shape_dist_traveled": "13.6090"}, {"shape_pt_lat": "30.232081", "shape_id": "39068", "shape_pt_lon": "-97.880388", "shape_pt_sequence": "449", "shape_dist_traveled": "13.7871"}, {"shape_pt_lat": "30.232153", "shape_id": "39068", "shape_pt_lon": "-97.880436", "shape_pt_sequence": "450", "shape_dist_traveled": "13.7965"}, {"shape_pt_lat": "30.232190", "shape_id": "39068", "shape_pt_lon": "-97.880535", "shape_pt_sequence": "451", "shape_dist_traveled": "13.8068"}, {"shape_pt_lat": "30.232191", "shape_id": "39068", "shape_pt_lon": "-97.880642", "shape_pt_sequence": "452", "shape_dist_traveled": "13.8178"}, {"shape_pt_lat": "30.232135", "shape_id": "39068", "shape_pt_lon": "-97.880766", "shape_pt_sequence": "453", "shape_dist_traveled": "13.8312"}, {"shape_pt_lat": "30.231675", "shape_id": "39068", "shape_pt_lon": "-97.881489", "shape_pt_sequence": "454", "shape_dist_traveled": "13.9170"}, {"shape_pt_lat": "30.231344", "shape_id": "39068", "shape_pt_lon": "-97.882046", "shape_pt_sequence": "455", "shape_dist_traveled": "13.9825"}, {"shape_pt_lat": "30.231210", "shape_id": "39068", "shape_pt_lon": "-97.882303", "shape_pt_sequence": "456", "shape_dist_traveled": "14.0116"}, {"shape_pt_lat": "30.231161", "shape_id": "39068", "shape_pt_lon": "-97.882510", "shape_pt_sequence": "457", "shape_dist_traveled": "14.0313"}, {"shape_pt_lat": "30.231163", "shape_id": "39068", "shape_pt_lon": "-97.882683", "shape_pt_sequence": "458", "shape_dist_traveled": "14.0483"}, {"shape_pt_lat": "30.231179", "shape_id": "39068", "shape_pt_lon": "-97.882914", "shape_pt_sequence": "459", "shape_dist_traveled": "14.0704"}, {"shape_pt_lat": "30.231216", "shape_id": "39068", "shape_pt_lon": "-97.883086", "shape_pt_sequence": "460", "shape_dist_traveled": "14.0878"}, {"shape_pt_lat": "30.231261", "shape_id": "39068", "shape_pt_lon": "-97.883226", "shape_pt_sequence": "461", "shape_dist_traveled": "14.1018"}, {"shape_pt_lat": "30.231348", "shape_id": "39068", "shape_pt_lon": "-97.883349", "shape_pt_sequence": "462", "shape_dist_traveled": "14.1174"}, {"shape_pt_lat": "30.231413", "shape_id": "39068", "shape_pt_lon": "-97.883464", "shape_pt_sequence": "463", "shape_dist_traveled": "14.1304"}]
