[{"shape_pt_lat": "30.357253", "shape_id": "38661", "shape_pt_lon": "-97.737607", "shape_pt_sequence": "1", "shape_dist_traveled": "0.0000"}, {"shape_pt_lat": "30.357756", "shape_id": "38661", "shape_pt_lon": "-97.738756", "shape_pt_sequence": "2", "shape_dist_traveled": "0.1239"}, {"shape_pt_lat": "30.357887", "shape_id": "38661", "shape_pt_lon": "-97.738684", "shape_pt_sequence": "3", "shape_dist_traveled": "0.1404"}, {"shape_pt_lat": "30.358037", "shape_id": "38661", "shape_pt_lon": "-97.738596", "shape_pt_sequence": "4", "shape_dist_traveled": "0.1597"}, {"shape_pt_lat": "30.358166", "shape_id": "38661", "shape_pt_lon": "-97.738535", "shape_pt_sequence": "5", "shape_dist_traveled": "0.1749"}, {"shape_pt_lat": "30.358283", "shape_id": "38661", "shape_pt_lon": "-97.738493", "shape_pt_sequence": "6", "shape_dist_traveled": "0.1885"}, {"shape_pt_lat": "30.358400", "shape_id": "38661", "shape_pt_lon": "-97.738465", "shape_pt_sequence": "7", "shape_dist_traveled": "0.2017"}, {"shape_pt_lat": "30.358517", "shape_id": "38661", "shape_pt_lon": "-97.738451", "shape_pt_sequence": "8", "shape_dist_traveled": "0.2148"}, {"shape_pt_lat": "30.358635", "shape_id": "38661", "shape_pt_lon": "-97.738450", "shape_pt_sequence": "9", "shape_dist_traveled": "0.2278"}, {"shape_pt_lat": "30.358791", "shape_id": "38661", "shape_pt_lon": "-97.738472", "shape_pt_sequence": "10", "shape_dist_traveled": "0.2449"}, {"shape_pt_lat": "30.358928", "shape_id": "38661", "shape_pt_lon": "-97.738494", "shape_pt_sequence": "11", "shape_dist_traveled": "0.2610"}, {"shape_pt_lat": "30.359042", "shape_id": "38661", "shape_pt_lon": "-97.738503", "shape_pt_sequence": "12", "shape_dist_traveled": "0.2731"}, {"shape_pt_lat": "30.359157", "shape_id": "38661", "shape_pt_lon": "-97.738497", "shape_pt_sequence": "13", "shape_dist_traveled": "0.2861"}, {"shape_pt_lat": "30.359258", "shape_id": "38661", "shape_pt_lon": "-97.738483", "shape_pt_sequence": "14", "shape_dist_traveled": "0.2973"}, {"shape_pt_lat": "30.359309", "shape_id": "38661", "shape_pt_lon": "-97.738465", "shape_pt_sequence": "15", "shape_dist_traveled": "0.3034"}, {"shape_pt_lat": "30.359379", "shape_id": "38661", "shape_pt_lon": "-97.738441", "shape_pt_sequence": "16", "shape_dist_traveled": "0.3119"}, {"shape_pt_lat": "30.359570", "shape_id": "38661", "shape_pt_lon": "-97.738345", "shape_pt_sequence": "17", "shape_dist_traveled": "0.3347"}, {"shape_pt_lat": "30.359648", "shape_id": "38661", "shape_pt_lon": "-97.738298", "shape_pt_sequence": "18", "shape_dist_traveled": "0.3450"}, {"shape_pt_lat": "30.359176", "shape_id": "38661", "shape_pt_lon": "-97.737381", "shape_pt_sequence": "19", "shape_dist_traveled": "0.4478"}, {"shape_pt_lat": "30.358981", "shape_id": "38661", "shape_pt_lon": "-97.737002", "shape_pt_sequence": "20", "shape_dist_traveled": "0.4900"}, {"shape_pt_lat": "30.358506", "shape_id": "38661", "shape_pt_lon": "-97.736099", "shape_pt_sequence": "21", "shape_dist_traveled": "0.5905"}, {"shape_pt_lat": "30.358230", "shape_id": "38661", "shape_pt_lon": "-97.735573", "shape_pt_sequence": "22", "shape_dist_traveled": "0.6501"}, {"shape_pt_lat": "30.357878", "shape_id": "38661", "shape_pt_lon": "-97.734819", "shape_pt_sequence": "23", "shape_dist_traveled": "0.7320"}, {"shape_pt_lat": "30.357816", "shape_id": "38661", "shape_pt_lon": "-97.734685", "shape_pt_sequence": "24", "shape_dist_traveled": "0.7468"}, {"shape_pt_lat": "30.357677", "shape_id": "38661", "shape_pt_lon": "-97.734388", "shape_pt_sequence": "25", "shape_dist_traveled": "0.7799"}, {"shape_pt_lat": "30.357489", "shape_id": "38661", "shape_pt_lon": "-97.733982", "shape_pt_sequence": "26", "shape_dist_traveled": "0.8237"}, {"shape_pt_lat": "30.357391", "shape_id": "38661", "shape_pt_lon": "-97.733765", "shape_pt_sequence": "27", "shape_dist_traveled": "0.8466"}, {"shape_pt_lat": "30.357068", "shape_id": "38661", "shape_pt_lon": "-97.733074", "shape_pt_sequence": "28", "shape_dist_traveled": "0.9226"}, {"shape_pt_lat": "30.356998", "shape_id": "38661", "shape_pt_lon": "-97.732926", "shape_pt_sequence": "29", "shape_dist_traveled": "0.9387"}, {"shape_pt_lat": "30.356843", "shape_id": "38661", "shape_pt_lon": "-97.732593", "shape_pt_sequence": "30", "shape_dist_traveled": "0.9750"}, {"shape_pt_lat": "30.356803", "shape_id": "38661", "shape_pt_lon": "-97.732506", "shape_pt_sequence": "31", "shape_dist_traveled": "0.9844"}, {"shape_pt_lat": "30.356346", "shape_id": "38661", "shape_pt_lon": "-97.731523", "shape_pt_sequence": "32", "shape_dist_traveled": "1.0918"}, {"shape_pt_lat": "30.356295", "shape_id": "38661", "shape_pt_lon": "-97.731414", "shape_pt_sequence": "33", "shape_dist_traveled": "1.1034"}, {"shape_pt_lat": "30.356231", "shape_id": "38661", "shape_pt_lon": "-97.731276", "shape_pt_sequence": "34", "shape_dist_traveled": "1.1182"}, {"shape_pt_lat": "30.356077", "shape_id": "38661", "shape_pt_lon": "-97.730927", "shape_pt_sequence": "35", "shape_dist_traveled": "1.1562"}, {"shape_pt_lat": "30.356123", "shape_id": "38661", "shape_pt_lon": "-97.730910", "shape_pt_sequence": "36", "shape_dist_traveled": "1.1613"}, {"shape_pt_lat": "30.356167", "shape_id": "38661", "shape_pt_lon": "-97.730892", "shape_pt_sequence": "37", "shape_dist_traveled": "1.1667"}, {"shape_pt_lat": "30.356451", "shape_id": "38661", "shape_pt_lon": "-97.730799", "shape_pt_sequence": "38", "shape_dist_traveled": "1.1990"}, {"shape_pt_lat": "30.356486", "shape_id": "38661", "shape_pt_lon": "-97.730787", "shape_pt_sequence": "39", "shape_dist_traveled": "1.2031"}, {"shape_pt_lat": "30.356529", "shape_id": "38661", "shape_pt_lon": "-97.730773", "shape_pt_sequence": "40", "shape_dist_traveled": "1.2082"}, {"shape_pt_lat": "30.356624", "shape_id": "38661", "shape_pt_lon": "-97.730737", "shape_pt_sequence": "41", "shape_dist_traveled": "1.2190"}, {"shape_pt_lat": "30.357369", "shape_id": "38661", "shape_pt_lon": "-97.730508", "shape_pt_sequence": "42", "shape_dist_traveled": "1.3048"}, {"shape_pt_lat": "30.357457", "shape_id": "38661", "shape_pt_lon": "-97.730484", "shape_pt_sequence": "43", "shape_dist_traveled": "1.3150"}, {"shape_pt_lat": "30.358075", "shape_id": "38661", "shape_pt_lon": "-97.730327", "shape_pt_sequence": "44", "shape_dist_traveled": "1.3847"}, {"shape_pt_lat": "30.358568", "shape_id": "38661", "shape_pt_lon": "-97.730200", "shape_pt_sequence": "45", "shape_dist_traveled": "1.4412"}, {"shape_pt_lat": "30.358749", "shape_id": "38661", "shape_pt_lon": "-97.730153", "shape_pt_sequence": "46", "shape_dist_traveled": "1.4616"}, {"shape_pt_lat": "30.360002", "shape_id": "38661", "shape_pt_lon": "-97.729832", "shape_pt_sequence": "47", "shape_dist_traveled": "1.6040"}, {"shape_pt_lat": "30.360924", "shape_id": "38661", "shape_pt_lon": "-97.729584", "shape_pt_sequence": "48", "shape_dist_traveled": "1.7098"}, {"shape_pt_lat": "30.361827", "shape_id": "38661", "shape_pt_lon": "-97.729341", "shape_pt_sequence": "49", "shape_dist_traveled": "1.8124"}, {"shape_pt_lat": "30.361890", "shape_id": "38661", "shape_pt_lon": "-97.729325", "shape_pt_sequence": "50", "shape_dist_traveled": "1.8196"}, {"shape_pt_lat": "30.362298", "shape_id": "38661", "shape_pt_lon": "-97.729222", "shape_pt_sequence": "51", "shape_dist_traveled": "1.8657"}, {"shape_pt_lat": "30.362581", "shape_id": "38661", "shape_pt_lon": "-97.729149", "shape_pt_sequence": "52", "shape_dist_traveled": "1.8985"}, {"shape_pt_lat": "30.362831", "shape_id": "38661", "shape_pt_lon": "-97.729086", "shape_pt_sequence": "53", "shape_dist_traveled": "1.9271"}, {"shape_pt_lat": "30.362828", "shape_id": "38661", "shape_pt_lon": "-97.728957", "shape_pt_sequence": "54", "shape_dist_traveled": "1.9392"}, {"shape_pt_lat": "30.362820", "shape_id": "38661", "shape_pt_lon": "-97.728871", "shape_pt_sequence": "55", "shape_dist_traveled": "1.9472"}, {"shape_pt_lat": "30.362804", "shape_id": "38661", "shape_pt_lon": "-97.728761", "shape_pt_sequence": "56", "shape_dist_traveled": "1.9583"}, {"shape_pt_lat": "30.362768", "shape_id": "38661", "shape_pt_lon": "-97.728628", "shape_pt_sequence": "57", "shape_dist_traveled": "1.9719"}, {"shape_pt_lat": "30.362745", "shape_id": "38661", "shape_pt_lon": "-97.728553", "shape_pt_sequence": "58", "shape_dist_traveled": "1.9795"}, {"shape_pt_lat": "30.362725", "shape_id": "38661", "shape_pt_lon": "-97.728487", "shape_pt_sequence": "59", "shape_dist_traveled": "1.9858"}, {"shape_pt_lat": "30.362675", "shape_id": "38661", "shape_pt_lon": "-97.728357", "shape_pt_sequence": "60", "shape_dist_traveled": "2.0001"}, {"shape_pt_lat": "30.362615", "shape_id": "38661", "shape_pt_lon": "-97.728224", "shape_pt_sequence": "61", "shape_dist_traveled": "2.0136"}, {"shape_pt_lat": "30.362554", "shape_id": "38661", "shape_pt_lon": "-97.728087", "shape_pt_sequence": "62", "shape_dist_traveled": "2.0292"}, {"shape_pt_lat": "30.362192", "shape_id": "38661", "shape_pt_lon": "-97.727346", "shape_pt_sequence": "63", "shape_dist_traveled": "2.1107"}, {"shape_pt_lat": "30.361816", "shape_id": "38661", "shape_pt_lon": "-97.726571", "shape_pt_sequence": "64", "shape_dist_traveled": "2.1958"}, {"shape_pt_lat": "30.361694", "shape_id": "38661", "shape_pt_lon": "-97.726309", "shape_pt_sequence": "65", "shape_dist_traveled": "2.2244"}, {"shape_pt_lat": "30.361619", "shape_id": "38661", "shape_pt_lon": "-97.726146", "shape_pt_sequence": "66", "shape_dist_traveled": "2.2423"}, {"shape_pt_lat": "30.361569", "shape_id": "38661", "shape_pt_lon": "-97.726032", "shape_pt_sequence": "67", "shape_dist_traveled": "2.2549"}, {"shape_pt_lat": "30.361540", "shape_id": "38661", "shape_pt_lon": "-97.725942", "shape_pt_sequence": "68", "shape_dist_traveled": "2.2634"}, {"shape_pt_lat": "30.361506", "shape_id": "38661", "shape_pt_lon": "-97.725837", "shape_pt_sequence": "69", "shape_dist_traveled": "2.2742"}, {"shape_pt_lat": "30.361480", "shape_id": "38661", "shape_pt_lon": "-97.725749", "shape_pt_sequence": "70", "shape_dist_traveled": "2.2837"}, {"shape_pt_lat": "30.361438", "shape_id": "38661", "shape_pt_lon": "-97.725585", "shape_pt_sequence": "71", "shape_dist_traveled": "2.3002"}, {"shape_pt_lat": "30.361380", "shape_id": "38661", "shape_pt_lon": "-97.725394", "shape_pt_sequence": "72", "shape_dist_traveled": "2.3195"}, {"shape_pt_lat": "30.361322", "shape_id": "38661", "shape_pt_lon": "-97.725231", "shape_pt_sequence": "73", "shape_dist_traveled": "2.3366"}, {"shape_pt_lat": "30.361272", "shape_id": "38661", "shape_pt_lon": "-97.725091", "shape_pt_sequence": "74", "shape_dist_traveled": "2.3509"}, {"shape_pt_lat": "30.361262", "shape_id": "38661", "shape_pt_lon": "-97.725068", "shape_pt_sequence": "75", "shape_dist_traveled": "2.3531"}, {"shape_pt_lat": "30.361214", "shape_id": "38661", "shape_pt_lon": "-97.724969", "shape_pt_sequence": "76", "shape_dist_traveled": "2.3643"}, {"shape_pt_lat": "30.361169", "shape_id": "38661", "shape_pt_lon": "-97.724856", "shape_pt_sequence": "77", "shape_dist_traveled": "2.3764"}, {"shape_pt_lat": "30.361104", "shape_id": "38661", "shape_pt_lon": "-97.724709", "shape_pt_sequence": "78", "shape_dist_traveled": "2.3920"}, {"shape_pt_lat": "30.361059", "shape_id": "38661", "shape_pt_lon": "-97.724610", "shape_pt_sequence": "79", "shape_dist_traveled": "2.4023"}, {"shape_pt_lat": "30.361045", "shape_id": "38661", "shape_pt_lon": "-97.724578", "shape_pt_sequence": "80", "shape_dist_traveled": "2.4059"}, {"shape_pt_lat": "30.360990", "shape_id": "38661", "shape_pt_lon": "-97.724428", "shape_pt_sequence": "81", "shape_dist_traveled": "2.4221"}, {"shape_pt_lat": "30.360969", "shape_id": "38661", "shape_pt_lon": "-97.724359", "shape_pt_sequence": "82", "shape_dist_traveled": "2.4284"}, {"shape_pt_lat": "30.360947", "shape_id": "38661", "shape_pt_lon": "-97.724274", "shape_pt_sequence": "83", "shape_dist_traveled": "2.4370"}, {"shape_pt_lat": "30.360925", "shape_id": "38661", "shape_pt_lon": "-97.724137", "shape_pt_sequence": "84", "shape_dist_traveled": "2.4511"}, {"shape_pt_lat": "30.360914", "shape_id": "38661", "shape_pt_lon": "-97.724020", "shape_pt_sequence": "85", "shape_dist_traveled": "2.4623"}, {"shape_pt_lat": "30.360909", "shape_id": "38661", "shape_pt_lon": "-97.723976", "shape_pt_sequence": "86", "shape_dist_traveled": "2.4663"}, {"shape_pt_lat": "30.360904", "shape_id": "38661", "shape_pt_lon": "-97.723856", "shape_pt_sequence": "87", "shape_dist_traveled": "2.4783"}, {"shape_pt_lat": "30.360914", "shape_id": "38661", "shape_pt_lon": "-97.723733", "shape_pt_sequence": "88", "shape_dist_traveled": "2.4894"}, {"shape_pt_lat": "30.360933", "shape_id": "38661", "shape_pt_lon": "-97.723614", "shape_pt_sequence": "89", "shape_dist_traveled": "2.5017"}, {"shape_pt_lat": "30.360962", "shape_id": "38661", "shape_pt_lon": "-97.723497", "shape_pt_sequence": "90", "shape_dist_traveled": "2.5131"}, {"shape_pt_lat": "30.361018", "shape_id": "38661", "shape_pt_lon": "-97.723301", "shape_pt_sequence": "91", "shape_dist_traveled": "2.5331"}, {"shape_pt_lat": "30.361187", "shape_id": "38661", "shape_pt_lon": "-97.722832", "shape_pt_sequence": "92", "shape_dist_traveled": "2.5819"}, {"shape_pt_lat": "30.361346", "shape_id": "38661", "shape_pt_lon": "-97.722332", "shape_pt_sequence": "93", "shape_dist_traveled": "2.6328"}, {"shape_pt_lat": "30.361422", "shape_id": "38661", "shape_pt_lon": "-97.722110", "shape_pt_sequence": "94", "shape_dist_traveled": "2.6557"}, {"shape_pt_lat": "30.361484", "shape_id": "38661", "shape_pt_lon": "-97.721964", "shape_pt_sequence": "95", "shape_dist_traveled": "2.6713"}, {"shape_pt_lat": "30.361526", "shape_id": "38661", "shape_pt_lon": "-97.721874", "shape_pt_sequence": "96", "shape_dist_traveled": "2.6812"}, {"shape_pt_lat": "30.361618", "shape_id": "38661", "shape_pt_lon": "-97.721732", "shape_pt_sequence": "97", "shape_dist_traveled": "2.6982"}, {"shape_pt_lat": "30.361700", "shape_id": "38661", "shape_pt_lon": "-97.721609", "shape_pt_sequence": "98", "shape_dist_traveled": "2.7132"}, {"shape_pt_lat": "30.361799", "shape_id": "38661", "shape_pt_lon": "-97.721487", "shape_pt_sequence": "99", "shape_dist_traveled": "2.7295"}, {"shape_pt_lat": "30.361855", "shape_id": "38661", "shape_pt_lon": "-97.721423", "shape_pt_sequence": "100", "shape_dist_traveled": "2.7380"}, {"shape_pt_lat": "30.362029", "shape_id": "38661", "shape_pt_lon": "-97.721240", "shape_pt_sequence": "101", "shape_dist_traveled": "2.7641"}, {"shape_pt_lat": "30.362172", "shape_id": "38661", "shape_pt_lon": "-97.721080", "shape_pt_sequence": "102", "shape_dist_traveled": "2.7861"}, {"shape_pt_lat": "30.362274", "shape_id": "38661", "shape_pt_lon": "-97.720922", "shape_pt_sequence": "103", "shape_dist_traveled": "2.8047"}, {"shape_pt_lat": "30.362341", "shape_id": "38661", "shape_pt_lon": "-97.720778", "shape_pt_sequence": "104", "shape_dist_traveled": "2.8208"}, {"shape_pt_lat": "30.362375", "shape_id": "38661", "shape_pt_lon": "-97.720689", "shape_pt_sequence": "105", "shape_dist_traveled": "2.8297"}, {"shape_pt_lat": "30.362465", "shape_id": "38661", "shape_pt_lon": "-97.720390", "shape_pt_sequence": "106", "shape_dist_traveled": "2.8604"}, {"shape_pt_lat": "30.362538", "shape_id": "38661", "shape_pt_lon": "-97.720135", "shape_pt_sequence": "107", "shape_dist_traveled": "2.8867"}, {"shape_pt_lat": "30.362583", "shape_id": "38661", "shape_pt_lon": "-97.719953", "shape_pt_sequence": "108", "shape_dist_traveled": "2.9044"}, {"shape_pt_lat": "30.362601", "shape_id": "38661", "shape_pt_lon": "-97.719889", "shape_pt_sequence": "109", "shape_dist_traveled": "2.9107"}, {"shape_pt_lat": "30.362618", "shape_id": "38661", "shape_pt_lon": "-97.719824", "shape_pt_sequence": "110", "shape_dist_traveled": "2.9180"}, {"shape_pt_lat": "30.362779", "shape_id": "38661", "shape_pt_lon": "-97.719234", "shape_pt_sequence": "111", "shape_dist_traveled": "2.9765"}, {"shape_pt_lat": "30.362865", "shape_id": "38661", "shape_pt_lon": "-97.718896", "shape_pt_sequence": "112", "shape_dist_traveled": "3.0110"}, {"shape_pt_lat": "30.362924", "shape_id": "38661", "shape_pt_lon": "-97.718666", "shape_pt_sequence": "113", "shape_dist_traveled": "3.0341"}, {"shape_pt_lat": "30.362903", "shape_id": "38661", "shape_pt_lon": "-97.718544", "shape_pt_sequence": "114", "shape_dist_traveled": "3.0455"}, {"shape_pt_lat": "30.362906", "shape_id": "38661", "shape_pt_lon": "-97.718518", "shape_pt_sequence": "115", "shape_dist_traveled": "3.0486"}, {"shape_pt_lat": "30.362970", "shape_id": "38661", "shape_pt_lon": "-97.718273", "shape_pt_sequence": "116", "shape_dist_traveled": "3.0727"}, {"shape_pt_lat": "30.363013", "shape_id": "38661", "shape_pt_lon": "-97.718110", "shape_pt_sequence": "117", "shape_dist_traveled": "3.0892"}, {"shape_pt_lat": "30.363070", "shape_id": "38661", "shape_pt_lon": "-97.717890", "shape_pt_sequence": "118", "shape_dist_traveled": "3.1113"}, {"shape_pt_lat": "30.363117", "shape_id": "38661", "shape_pt_lon": "-97.717710", "shape_pt_sequence": "119", "shape_dist_traveled": "3.1290"}, {"shape_pt_lat": "30.363130", "shape_id": "38661", "shape_pt_lon": "-97.717632", "shape_pt_sequence": "120", "shape_dist_traveled": "3.1371"}, {"shape_pt_lat": "30.363178", "shape_id": "38661", "shape_pt_lon": "-97.717442", "shape_pt_sequence": "121", "shape_dist_traveled": "3.1561"}, {"shape_pt_lat": "30.363208", "shape_id": "38661", "shape_pt_lon": "-97.717323", "shape_pt_sequence": "122", "shape_dist_traveled": "3.1684"}, {"shape_pt_lat": "30.363262", "shape_id": "38661", "shape_pt_lon": "-97.717082", "shape_pt_sequence": "123", "shape_dist_traveled": "3.1922"}, {"shape_pt_lat": "30.363319", "shape_id": "38661", "shape_pt_lon": "-97.716849", "shape_pt_sequence": "124", "shape_dist_traveled": "3.2150"}, {"shape_pt_lat": "30.363364", "shape_id": "38661", "shape_pt_lon": "-97.716677", "shape_pt_sequence": "125", "shape_dist_traveled": "3.2327"}, {"shape_pt_lat": "30.363425", "shape_id": "38661", "shape_pt_lon": "-97.716507", "shape_pt_sequence": "126", "shape_dist_traveled": "3.2502"}, {"shape_pt_lat": "30.363500", "shape_id": "38661", "shape_pt_lon": "-97.716428", "shape_pt_sequence": "127", "shape_dist_traveled": "3.2608"}, {"shape_pt_lat": "30.363523", "shape_id": "38661", "shape_pt_lon": "-97.716351", "shape_pt_sequence": "128", "shape_dist_traveled": "3.2694"}, {"shape_pt_lat": "30.363582", "shape_id": "38661", "shape_pt_lon": "-97.716176", "shape_pt_sequence": "129", "shape_dist_traveled": "3.2874"}, {"shape_pt_lat": "30.363601", "shape_id": "38661", "shape_pt_lon": "-97.716122", "shape_pt_sequence": "130", "shape_dist_traveled": "3.2932"}, {"shape_pt_lat": "30.363678", "shape_id": "38661", "shape_pt_lon": "-97.715923", "shape_pt_sequence": "131", "shape_dist_traveled": "3.3138"}, {"shape_pt_lat": "30.363736", "shape_id": "38661", "shape_pt_lon": "-97.715772", "shape_pt_sequence": "132", "shape_dist_traveled": "3.3295"}, {"shape_pt_lat": "30.363780", "shape_id": "38661", "shape_pt_lon": "-97.715672", "shape_pt_sequence": "133", "shape_dist_traveled": "3.3403"}, {"shape_pt_lat": "30.363831", "shape_id": "38661", "shape_pt_lon": "-97.715568", "shape_pt_sequence": "134", "shape_dist_traveled": "3.3519"}, {"shape_pt_lat": "30.363875", "shape_id": "38661", "shape_pt_lon": "-97.715495", "shape_pt_sequence": "135", "shape_dist_traveled": "3.3605"}, {"shape_pt_lat": "30.363936", "shape_id": "38661", "shape_pt_lon": "-97.715411", "shape_pt_sequence": "136", "shape_dist_traveled": "3.3712"}, {"shape_pt_lat": "30.363939", "shape_id": "38661", "shape_pt_lon": "-97.715405", "shape_pt_sequence": "137", "shape_dist_traveled": "3.3722"}, {"shape_pt_lat": "30.363979", "shape_id": "38661", "shape_pt_lon": "-97.715341", "shape_pt_sequence": "138", "shape_dist_traveled": "3.3800"}, {"shape_pt_lat": "30.364025", "shape_id": "38661", "shape_pt_lon": "-97.715255", "shape_pt_sequence": "139", "shape_dist_traveled": "3.3894"}, {"shape_pt_lat": "30.364042", "shape_id": "38661", "shape_pt_lon": "-97.715223", "shape_pt_sequence": "140", "shape_dist_traveled": "3.3930"}, {"shape_pt_lat": "30.364087", "shape_id": "38661", "shape_pt_lon": "-97.715140", "shape_pt_sequence": "141", "shape_dist_traveled": "3.4025"}, {"shape_pt_lat": "30.364129", "shape_id": "38661", "shape_pt_lon": "-97.715048", "shape_pt_sequence": "142", "shape_dist_traveled": "3.4123"}, {"shape_pt_lat": "30.364161", "shape_id": "38661", "shape_pt_lon": "-97.714956", "shape_pt_sequence": "143", "shape_dist_traveled": "3.4221"}, {"shape_pt_lat": "30.364182", "shape_id": "38661", "shape_pt_lon": "-97.714890", "shape_pt_sequence": "144", "shape_dist_traveled": "3.4285"}, {"shape_pt_lat": "30.364213", "shape_id": "38661", "shape_pt_lon": "-97.714840", "shape_pt_sequence": "145", "shape_dist_traveled": "3.4349"}, {"shape_pt_lat": "30.364226", "shape_id": "38661", "shape_pt_lon": "-97.714788", "shape_pt_sequence": "146", "shape_dist_traveled": "3.4400"}, {"shape_pt_lat": "30.364241", "shape_id": "38661", "shape_pt_lon": "-97.714712", "shape_pt_sequence": "147", "shape_dist_traveled": "3.4473"}, {"shape_pt_lat": "30.364250", "shape_id": "38661", "shape_pt_lon": "-97.714676", "shape_pt_sequence": "148", "shape_dist_traveled": "3.4514"}, {"shape_pt_lat": "30.364253", "shape_id": "38661", "shape_pt_lon": "-97.714609", "shape_pt_sequence": "149", "shape_dist_traveled": "3.4574"}, {"shape_pt_lat": "30.364257", "shape_id": "38661", "shape_pt_lon": "-97.714558", "shape_pt_sequence": "150", "shape_dist_traveled": "3.4624"}, {"shape_pt_lat": "30.364256", "shape_id": "38661", "shape_pt_lon": "-97.714503", "shape_pt_sequence": "151", "shape_dist_traveled": "3.4674"}, {"shape_pt_lat": "30.364252", "shape_id": "38661", "shape_pt_lon": "-97.714442", "shape_pt_sequence": "152", "shape_dist_traveled": "3.4734"}, {"shape_pt_lat": "30.364494", "shape_id": "38661", "shape_pt_lon": "-97.714940", "shape_pt_sequence": "153", "shape_dist_traveled": "3.5285"}, {"shape_pt_lat": "30.364891", "shape_id": "38661", "shape_pt_lon": "-97.715691", "shape_pt_sequence": "154", "shape_dist_traveled": "3.6128"}, {"shape_pt_lat": "30.365279", "shape_id": "38661", "shape_pt_lon": "-97.716602", "shape_pt_sequence": "155", "shape_dist_traveled": "3.7099"}, {"shape_pt_lat": "30.365921", "shape_id": "38661", "shape_pt_lon": "-97.716063", "shape_pt_sequence": "156", "shape_dist_traveled": "3.7979"}, {"shape_pt_lat": "30.368819", "shape_id": "38661", "shape_pt_lon": "-97.714197", "shape_pt_sequence": "157", "shape_dist_traveled": "4.1663"}, {"shape_pt_lat": "30.368909", "shape_id": "38661", "shape_pt_lon": "-97.714258", "shape_pt_sequence": "158", "shape_dist_traveled": "4.1780"}, {"shape_pt_lat": "30.368977", "shape_id": "38661", "shape_pt_lon": "-97.714331", "shape_pt_sequence": "159", "shape_dist_traveled": "4.1886"}, {"shape_pt_lat": "30.369109", "shape_id": "38661", "shape_pt_lon": "-97.714542", "shape_pt_sequence": "160", "shape_dist_traveled": "4.2130"}, {"shape_pt_lat": "30.369396", "shape_id": "38661", "shape_pt_lon": "-97.715194", "shape_pt_sequence": "161", "shape_dist_traveled": "4.2837"}, {"shape_pt_lat": "30.369463", "shape_id": "38661", "shape_pt_lon": "-97.715451", "shape_pt_sequence": "162", "shape_dist_traveled": "4.3099"}, {"shape_pt_lat": "30.369510", "shape_id": "38661", "shape_pt_lon": "-97.715604", "shape_pt_sequence": "163", "shape_dist_traveled": "4.3248"}, {"shape_pt_lat": "30.369537", "shape_id": "38661", "shape_pt_lon": "-97.715695", "shape_pt_sequence": "164", "shape_dist_traveled": "4.3343"}, {"shape_pt_lat": "30.369554", "shape_id": "38661", "shape_pt_lon": "-97.715757", "shape_pt_sequence": "165", "shape_dist_traveled": "4.3406"}, {"shape_pt_lat": "30.369571", "shape_id": "38661", "shape_pt_lon": "-97.715832", "shape_pt_sequence": "166", "shape_dist_traveled": "4.3479"}, {"shape_pt_lat": "30.369583", "shape_id": "38661", "shape_pt_lon": "-97.715918", "shape_pt_sequence": "167", "shape_dist_traveled": "4.3559"}, {"shape_pt_lat": "30.369595", "shape_id": "38661", "shape_pt_lon": "-97.716005", "shape_pt_sequence": "168", "shape_dist_traveled": "4.3650"}, {"shape_pt_lat": "30.369604", "shape_id": "38661", "shape_pt_lon": "-97.716083", "shape_pt_sequence": "169", "shape_dist_traveled": "4.3721"}, {"shape_pt_lat": "30.369645", "shape_id": "38661", "shape_pt_lon": "-97.716464", "shape_pt_sequence": "170", "shape_dist_traveled": "4.4094"}, {"shape_pt_lat": "30.369655", "shape_id": "38661", "shape_pt_lon": "-97.716573", "shape_pt_sequence": "171", "shape_dist_traveled": "4.4194"}, {"shape_pt_lat": "30.369663", "shape_id": "38661", "shape_pt_lon": "-97.716622", "shape_pt_sequence": "172", "shape_dist_traveled": "4.4245"}, {"shape_pt_lat": "30.369672", "shape_id": "38661", "shape_pt_lon": "-97.716661", "shape_pt_sequence": "173", "shape_dist_traveled": "4.4287"}, {"shape_pt_lat": "30.369685", "shape_id": "38661", "shape_pt_lon": "-97.716721", "shape_pt_sequence": "174", "shape_dist_traveled": "4.4338"}, {"shape_pt_lat": "30.369695", "shape_id": "38661", "shape_pt_lon": "-97.716762", "shape_pt_sequence": "175", "shape_dist_traveled": "4.4379"}, {"shape_pt_lat": "30.369712", "shape_id": "38661", "shape_pt_lon": "-97.716808", "shape_pt_sequence": "176", "shape_dist_traveled": "4.4433"}, {"shape_pt_lat": "30.369729", "shape_id": "38661", "shape_pt_lon": "-97.716844", "shape_pt_sequence": "177", "shape_dist_traveled": "4.4469"}, {"shape_pt_lat": "30.369799", "shape_id": "38661", "shape_pt_lon": "-97.716997", "shape_pt_sequence": "178", "shape_dist_traveled": "4.4639"}, {"shape_pt_lat": "30.370280", "shape_id": "38661", "shape_pt_lon": "-97.716671", "shape_pt_sequence": "179", "shape_dist_traveled": "4.5253"}, {"shape_pt_lat": "30.370496", "shape_id": "38661", "shape_pt_lon": "-97.716527", "shape_pt_sequence": "180", "shape_dist_traveled": "4.5531"}, {"shape_pt_lat": "30.371939", "shape_id": "38661", "shape_pt_lon": "-97.715622", "shape_pt_sequence": "181", "shape_dist_traveled": "4.7361"}, {"shape_pt_lat": "30.371833", "shape_id": "38661", "shape_pt_lon": "-97.715396", "shape_pt_sequence": "182", "shape_dist_traveled": "4.7611"}, {"shape_pt_lat": "30.371382", "shape_id": "38661", "shape_pt_lon": "-97.714471", "shape_pt_sequence": "183", "shape_dist_traveled": "4.8623"}, {"shape_pt_lat": "30.371233", "shape_id": "38661", "shape_pt_lon": "-97.714157", "shape_pt_sequence": "184", "shape_dist_traveled": "4.8977"}, {"shape_pt_lat": "30.371178", "shape_id": "38661", "shape_pt_lon": "-97.714055", "shape_pt_sequence": "185", "shape_dist_traveled": "4.9085"}, {"shape_pt_lat": "30.371115", "shape_id": "38661", "shape_pt_lon": "-97.713939", "shape_pt_sequence": "186", "shape_dist_traveled": "4.9224"}, {"shape_pt_lat": "30.371027", "shape_id": "38661", "shape_pt_lon": "-97.713795", "shape_pt_sequence": "187", "shape_dist_traveled": "4.9388"}, {"shape_pt_lat": "30.370977", "shape_id": "38661", "shape_pt_lon": "-97.713725", "shape_pt_sequence": "188", "shape_dist_traveled": "4.9474"}, {"shape_pt_lat": "30.370883", "shape_id": "38661", "shape_pt_lon": "-97.713607", "shape_pt_sequence": "189", "shape_dist_traveled": "4.9630"}, {"shape_pt_lat": "30.370747", "shape_id": "38661", "shape_pt_lon": "-97.713458", "shape_pt_sequence": "190", "shape_dist_traveled": "4.9842"}, {"shape_pt_lat": "30.370741", "shape_id": "38661", "shape_pt_lon": "-97.713451", "shape_pt_sequence": "191", "shape_dist_traveled": "4.9852"}, {"shape_pt_lat": "30.370455", "shape_id": "38661", "shape_pt_lon": "-97.713097", "shape_pt_sequence": "192", "shape_dist_traveled": "5.0312"}, {"shape_pt_lat": "30.370258", "shape_id": "38661", "shape_pt_lon": "-97.712763", "shape_pt_sequence": "193", "shape_dist_traveled": "5.0700"}, {"shape_pt_lat": "30.370049", "shape_id": "38661", "shape_pt_lon": "-97.712358", "shape_pt_sequence": "194", "shape_dist_traveled": "5.1153"}, {"shape_pt_lat": "30.369646", "shape_id": "38661", "shape_pt_lon": "-97.711519", "shape_pt_sequence": "195", "shape_dist_traveled": "5.2080"}, {"shape_pt_lat": "30.369237", "shape_id": "38661", "shape_pt_lon": "-97.710661", "shape_pt_sequence": "196", "shape_dist_traveled": "5.3020"}, {"shape_pt_lat": "30.369339", "shape_id": "38661", "shape_pt_lon": "-97.710609", "shape_pt_sequence": "197", "shape_dist_traveled": "5.3150"}, {"shape_pt_lat": "30.371197", "shape_id": "38661", "shape_pt_lon": "-97.709474", "shape_pt_sequence": "198", "shape_dist_traveled": "5.5480"}, {"shape_pt_lat": "30.372885", "shape_id": "38661", "shape_pt_lon": "-97.708367", "shape_pt_sequence": "199", "shape_dist_traveled": "5.7630"}, {"shape_pt_lat": "30.373183", "shape_id": "38661", "shape_pt_lon": "-97.708172", "shape_pt_sequence": "200", "shape_dist_traveled": "5.8019"}, {"shape_pt_lat": "30.373637", "shape_id": "38661", "shape_pt_lon": "-97.707868", "shape_pt_sequence": "201", "shape_dist_traveled": "5.8597"}, {"shape_pt_lat": "30.374036", "shape_id": "38661", "shape_pt_lon": "-97.707614", "shape_pt_sequence": "202", "shape_dist_traveled": "5.9103"}, {"shape_pt_lat": "30.374321", "shape_id": "38661", "shape_pt_lon": "-97.707425", "shape_pt_sequence": "203", "shape_dist_traveled": "5.9471"}, {"shape_pt_lat": "30.374742", "shape_id": "38661", "shape_pt_lon": "-97.707151", "shape_pt_sequence": "204", "shape_dist_traveled": "6.0008"}, {"shape_pt_lat": "30.374914", "shape_id": "38661", "shape_pt_lon": "-97.707043", "shape_pt_sequence": "205", "shape_dist_traveled": "6.0222"}, {"shape_pt_lat": "30.375009", "shape_id": "38661", "shape_pt_lon": "-97.706976", "shape_pt_sequence": "206", "shape_dist_traveled": "6.0344"}, {"shape_pt_lat": "30.375070", "shape_id": "38661", "shape_pt_lon": "-97.706926", "shape_pt_sequence": "207", "shape_dist_traveled": "6.0431"}, {"shape_pt_lat": "30.375126", "shape_id": "38661", "shape_pt_lon": "-97.706877", "shape_pt_sequence": "208", "shape_dist_traveled": "6.0503"}, {"shape_pt_lat": "30.375177", "shape_id": "38661", "shape_pt_lon": "-97.706828", "shape_pt_sequence": "209", "shape_dist_traveled": "6.0581"}, {"shape_pt_lat": "30.375230", "shape_id": "38661", "shape_pt_lon": "-97.706770", "shape_pt_sequence": "210", "shape_dist_traveled": "6.0666"}, {"shape_pt_lat": "30.375268", "shape_id": "38661", "shape_pt_lon": "-97.706720", "shape_pt_sequence": "211", "shape_dist_traveled": "6.0722"}, {"shape_pt_lat": "30.375307", "shape_id": "38661", "shape_pt_lon": "-97.706664", "shape_pt_sequence": "212", "shape_dist_traveled": "6.0794"}, {"shape_pt_lat": "30.375338", "shape_id": "38661", "shape_pt_lon": "-97.706620", "shape_pt_sequence": "213", "shape_dist_traveled": "6.0851"}, {"shape_pt_lat": "30.375376", "shape_id": "38661", "shape_pt_lon": "-97.706558", "shape_pt_sequence": "214", "shape_dist_traveled": "6.0923"}, {"shape_pt_lat": "30.375407", "shape_id": "38661", "shape_pt_lon": "-97.706508", "shape_pt_sequence": "215", "shape_dist_traveled": "6.0981"}, {"shape_pt_lat": "30.375442", "shape_id": "38661", "shape_pt_lon": "-97.706430", "shape_pt_sequence": "216", "shape_dist_traveled": "6.1062"}, {"shape_pt_lat": "30.375491", "shape_id": "38661", "shape_pt_lon": "-97.706317", "shape_pt_sequence": "217", "shape_dist_traveled": "6.1187"}, {"shape_pt_lat": "30.375598", "shape_id": "38661", "shape_pt_lon": "-97.706062", "shape_pt_sequence": "218", "shape_dist_traveled": "6.1456"}, {"shape_pt_lat": "30.375797", "shape_id": "38661", "shape_pt_lon": "-97.705580", "shape_pt_sequence": "219", "shape_dist_traveled": "6.1974"}, {"shape_pt_lat": "30.375891", "shape_id": "38661", "shape_pt_lon": "-97.705307", "shape_pt_sequence": "220", "shape_dist_traveled": "6.2253"}, {"shape_pt_lat": "30.376000", "shape_id": "38661", "shape_pt_lon": "-97.705015", "shape_pt_sequence": "221", "shape_dist_traveled": "6.2558"}, {"shape_pt_lat": "30.375673", "shape_id": "38661", "shape_pt_lon": "-97.704836", "shape_pt_sequence": "222", "shape_dist_traveled": "6.2956"}, {"shape_pt_lat": "30.375290", "shape_id": "38661", "shape_pt_lon": "-97.704627", "shape_pt_sequence": "223", "shape_dist_traveled": "6.3430"}, {"shape_pt_lat": "30.374967", "shape_id": "38661", "shape_pt_lon": "-97.704457", "shape_pt_sequence": "224", "shape_dist_traveled": "6.3815"}, {"shape_pt_lat": "30.374694", "shape_id": "38661", "shape_pt_lon": "-97.704310", "shape_pt_sequence": "225", "shape_dist_traveled": "6.4159"}, {"shape_pt_lat": "30.374452", "shape_id": "38661", "shape_pt_lon": "-97.704198", "shape_pt_sequence": "226", "shape_dist_traveled": "6.4447"}, {"shape_pt_lat": "30.374058", "shape_id": "38661", "shape_pt_lon": "-97.704072", "shape_pt_sequence": "227", "shape_dist_traveled": "6.4894"}, {"shape_pt_lat": "30.373763", "shape_id": "38661", "shape_pt_lon": "-97.703997", "shape_pt_sequence": "228", "shape_dist_traveled": "6.5233"}, {"shape_pt_lat": "30.373687", "shape_id": "38661", "shape_pt_lon": "-97.703979", "shape_pt_sequence": "229", "shape_dist_traveled": "6.5324"}, {"shape_pt_lat": "30.373443", "shape_id": "38661", "shape_pt_lon": "-97.703919", "shape_pt_sequence": "230", "shape_dist_traveled": "6.5600"}, {"shape_pt_lat": "30.373231", "shape_id": "38661", "shape_pt_lon": "-97.703871", "shape_pt_sequence": "231", "shape_dist_traveled": "6.5836"}, {"shape_pt_lat": "30.373051", "shape_id": "38661", "shape_pt_lon": "-97.703818", "shape_pt_sequence": "232", "shape_dist_traveled": "6.6042"}, {"shape_pt_lat": "30.372973", "shape_id": "38661", "shape_pt_lon": "-97.703797", "shape_pt_sequence": "233", "shape_dist_traveled": "6.6134"}, {"shape_pt_lat": "30.372882", "shape_id": "38661", "shape_pt_lon": "-97.703758", "shape_pt_sequence": "234", "shape_dist_traveled": "6.6238"}, {"shape_pt_lat": "30.372794", "shape_id": "38661", "shape_pt_lon": "-97.703719", "shape_pt_sequence": "235", "shape_dist_traveled": "6.6346"}, {"shape_pt_lat": "30.372616", "shape_id": "38661", "shape_pt_lon": "-97.703603", "shape_pt_sequence": "236", "shape_dist_traveled": "6.6574"}, {"shape_pt_lat": "30.372442", "shape_id": "38661", "shape_pt_lon": "-97.703478", "shape_pt_sequence": "237", "shape_dist_traveled": "6.6799"}, {"shape_pt_lat": "30.372334", "shape_id": "38661", "shape_pt_lon": "-97.703389", "shape_pt_sequence": "238", "shape_dist_traveled": "6.6949"}, {"shape_pt_lat": "30.372272", "shape_id": "38661", "shape_pt_lon": "-97.703338", "shape_pt_sequence": "239", "shape_dist_traveled": "6.7035"}, {"shape_pt_lat": "30.372114", "shape_id": "38661", "shape_pt_lon": "-97.703200", "shape_pt_sequence": "240", "shape_dist_traveled": "6.7249"}, {"shape_pt_lat": "30.371812", "shape_id": "38661", "shape_pt_lon": "-97.702927", "shape_pt_sequence": "241", "shape_dist_traveled": "6.7677"}, {"shape_pt_lat": "30.371604", "shape_id": "38661", "shape_pt_lon": "-97.702741", "shape_pt_sequence": "242", "shape_dist_traveled": "6.7969"}, {"shape_pt_lat": "30.371335", "shape_id": "38661", "shape_pt_lon": "-97.702499", "shape_pt_sequence": "243", "shape_dist_traveled": "6.8347"}, {"shape_pt_lat": "30.371253", "shape_id": "38661", "shape_pt_lon": "-97.702427", "shape_pt_sequence": "244", "shape_dist_traveled": "6.8461"}, {"shape_pt_lat": "30.370927", "shape_id": "38661", "shape_pt_lon": "-97.702168", "shape_pt_sequence": "245", "shape_dist_traveled": "6.8900"}, {"shape_pt_lat": "30.370821", "shape_id": "38661", "shape_pt_lon": "-97.702092", "shape_pt_sequence": "246", "shape_dist_traveled": "6.9038"}, {"shape_pt_lat": "30.370643", "shape_id": "38661", "shape_pt_lon": "-97.701964", "shape_pt_sequence": "247", "shape_dist_traveled": "6.9277"}, {"shape_pt_lat": "30.370402", "shape_id": "38661", "shape_pt_lon": "-97.701774", "shape_pt_sequence": "248", "shape_dist_traveled": "6.9593"}, {"shape_pt_lat": "30.370273", "shape_id": "38661", "shape_pt_lon": "-97.701644", "shape_pt_sequence": "249", "shape_dist_traveled": "6.9785"}, {"shape_pt_lat": "30.370202", "shape_id": "38661", "shape_pt_lon": "-97.701562", "shape_pt_sequence": "250", "shape_dist_traveled": "6.9898"}, {"shape_pt_lat": "30.370118", "shape_id": "38661", "shape_pt_lon": "-97.701457", "shape_pt_sequence": "251", "shape_dist_traveled": "7.0033"}, {"shape_pt_lat": "30.370007", "shape_id": "38661", "shape_pt_lon": "-97.701275", "shape_pt_sequence": "252", "shape_dist_traveled": "7.0249"}, {"shape_pt_lat": "30.369899", "shape_id": "38661", "shape_pt_lon": "-97.701067", "shape_pt_sequence": "253", "shape_dist_traveled": "7.0483"}, {"shape_pt_lat": "30.369819", "shape_id": "38661", "shape_pt_lon": "-97.700907", "shape_pt_sequence": "254", "shape_dist_traveled": "7.0657"}, {"shape_pt_lat": "30.369654", "shape_id": "38661", "shape_pt_lon": "-97.700593", "shape_pt_sequence": "255", "shape_dist_traveled": "7.1013"}, {"shape_pt_lat": "30.369539", "shape_id": "38661", "shape_pt_lon": "-97.700381", "shape_pt_sequence": "256", "shape_dist_traveled": "7.1246"}, {"shape_pt_lat": "30.369459", "shape_id": "38661", "shape_pt_lon": "-97.700225", "shape_pt_sequence": "257", "shape_dist_traveled": "7.1421"}, {"shape_pt_lat": "30.369426", "shape_id": "38661", "shape_pt_lon": "-97.700156", "shape_pt_sequence": "258", "shape_dist_traveled": "7.1501"}, {"shape_pt_lat": "30.369408", "shape_id": "38661", "shape_pt_lon": "-97.700114", "shape_pt_sequence": "259", "shape_dist_traveled": "7.1546"}, {"shape_pt_lat": "30.369395", "shape_id": "38661", "shape_pt_lon": "-97.700088", "shape_pt_sequence": "260", "shape_dist_traveled": "7.1578"}, {"shape_pt_lat": "30.369367", "shape_id": "38661", "shape_pt_lon": "-97.700033", "shape_pt_sequence": "261", "shape_dist_traveled": "7.1636"}, {"shape_pt_lat": "30.369334", "shape_id": "38661", "shape_pt_lon": "-97.699979", "shape_pt_sequence": "262", "shape_dist_traveled": "7.1700"}, {"shape_pt_lat": "30.369299", "shape_id": "38661", "shape_pt_lon": "-97.699935", "shape_pt_sequence": "263", "shape_dist_traveled": "7.1757"}, {"shape_pt_lat": "30.369264", "shape_id": "38661", "shape_pt_lon": "-97.699900", "shape_pt_sequence": "264", "shape_dist_traveled": "7.1813"}, {"shape_pt_lat": "30.369233", "shape_id": "38661", "shape_pt_lon": "-97.699870", "shape_pt_sequence": "265", "shape_dist_traveled": "7.1849"}, {"shape_pt_lat": "30.369202", "shape_id": "38661", "shape_pt_lon": "-97.699845", "shape_pt_sequence": "266", "shape_dist_traveled": "7.1899"}, {"shape_pt_lat": "30.369171", "shape_id": "38661", "shape_pt_lon": "-97.699823", "shape_pt_sequence": "267", "shape_dist_traveled": "7.1935"}, {"shape_pt_lat": "30.369145", "shape_id": "38661", "shape_pt_lon": "-97.699802", "shape_pt_sequence": "268", "shape_dist_traveled": "7.1971"}, {"shape_pt_lat": "30.369116", "shape_id": "38661", "shape_pt_lon": "-97.699786", "shape_pt_sequence": "269", "shape_dist_traveled": "7.2003"}, {"shape_pt_lat": "30.369080", "shape_id": "38661", "shape_pt_lon": "-97.699768", "shape_pt_sequence": "270", "shape_dist_traveled": "7.2048"}, {"shape_pt_lat": "30.369038", "shape_id": "38661", "shape_pt_lon": "-97.699753", "shape_pt_sequence": "271", "shape_dist_traveled": "7.2102"}, {"shape_pt_lat": "30.369006", "shape_id": "38661", "shape_pt_lon": "-97.699743", "shape_pt_sequence": "272", "shape_dist_traveled": "7.2143"}, {"shape_pt_lat": "30.368967", "shape_id": "38661", "shape_pt_lon": "-97.699736", "shape_pt_sequence": "273", "shape_dist_traveled": "7.2183"}, {"shape_pt_lat": "30.368913", "shape_id": "38661", "shape_pt_lon": "-97.699730", "shape_pt_sequence": "274", "shape_dist_traveled": "7.2244"}, {"shape_pt_lat": "30.368874", "shape_id": "38661", "shape_pt_lon": "-97.699728", "shape_pt_sequence": "275", "shape_dist_traveled": "7.2284"}, {"shape_pt_lat": "30.368830", "shape_id": "38661", "shape_pt_lon": "-97.699728", "shape_pt_sequence": "276", "shape_dist_traveled": "7.2334"}, {"shape_pt_lat": "30.368787", "shape_id": "38661", "shape_pt_lon": "-97.699735", "shape_pt_sequence": "277", "shape_dist_traveled": "7.2385"}, {"shape_pt_lat": "30.368736", "shape_id": "38661", "shape_pt_lon": "-97.699742", "shape_pt_sequence": "278", "shape_dist_traveled": "7.2445"}, {"shape_pt_lat": "30.368683", "shape_id": "38661", "shape_pt_lon": "-97.699758", "shape_pt_sequence": "279", "shape_dist_traveled": "7.2498"}, {"shape_pt_lat": "30.368625", "shape_id": "38661", "shape_pt_lon": "-97.699781", "shape_pt_sequence": "280", "shape_dist_traveled": "7.2571"}, {"shape_pt_lat": "30.368565", "shape_id": "38661", "shape_pt_lon": "-97.699812", "shape_pt_sequence": "281", "shape_dist_traveled": "7.2638"}, {"shape_pt_lat": "30.368493", "shape_id": "38661", "shape_pt_lon": "-97.699849", "shape_pt_sequence": "282", "shape_dist_traveled": "7.2728"}, {"shape_pt_lat": "30.368432", "shape_id": "38661", "shape_pt_lon": "-97.699884", "shape_pt_sequence": "283", "shape_dist_traveled": "7.2804"}, {"shape_pt_lat": "30.368339", "shape_id": "38661", "shape_pt_lon": "-97.699939", "shape_pt_sequence": "284", "shape_dist_traveled": "7.2925"}, {"shape_pt_lat": "30.368208", "shape_id": "38661", "shape_pt_lon": "-97.700018", "shape_pt_sequence": "285", "shape_dist_traveled": "7.3086"}, {"shape_pt_lat": "30.368070", "shape_id": "38661", "shape_pt_lon": "-97.700095", "shape_pt_sequence": "286", "shape_dist_traveled": "7.3252"}, {"shape_pt_lat": "30.367999", "shape_id": "38661", "shape_pt_lon": "-97.700135", "shape_pt_sequence": "287", "shape_dist_traveled": "7.3341"}, {"shape_pt_lat": "30.367920", "shape_id": "38661", "shape_pt_lon": "-97.700183", "shape_pt_sequence": "288", "shape_dist_traveled": "7.3444"}, {"shape_pt_lat": "30.367840", "shape_id": "38661", "shape_pt_lon": "-97.700226", "shape_pt_sequence": "289", "shape_dist_traveled": "7.3542"}, {"shape_pt_lat": "30.367744", "shape_id": "38661", "shape_pt_lon": "-97.700272", "shape_pt_sequence": "290", "shape_dist_traveled": "7.3659"}, {"shape_pt_lat": "30.367660", "shape_id": "38661", "shape_pt_lon": "-97.700308", "shape_pt_sequence": "291", "shape_dist_traveled": "7.3758"}, {"shape_pt_lat": "30.367573", "shape_id": "38661", "shape_pt_lon": "-97.700344", "shape_pt_sequence": "292", "shape_dist_traveled": "7.3862"}, {"shape_pt_lat": "30.367554", "shape_id": "38661", "shape_pt_lon": "-97.700350", "shape_pt_sequence": "293", "shape_dist_traveled": "7.3885"}, {"shape_pt_lat": "30.367407", "shape_id": "38661", "shape_pt_lon": "-97.700401", "shape_pt_sequence": "294", "shape_dist_traveled": "7.4052"}, {"shape_pt_lat": "30.367311", "shape_id": "38661", "shape_pt_lon": "-97.700436", "shape_pt_sequence": "295", "shape_dist_traveled": "7.4166"}, {"shape_pt_lat": "30.367261", "shape_id": "38661", "shape_pt_lon": "-97.700454", "shape_pt_sequence": "296", "shape_dist_traveled": "7.4220"}, {"shape_pt_lat": "30.367208", "shape_id": "38661", "shape_pt_lon": "-97.700478", "shape_pt_sequence": "297", "shape_dist_traveled": "7.4283"}, {"shape_pt_lat": "30.367145", "shape_id": "38661", "shape_pt_lon": "-97.700512", "shape_pt_sequence": "298", "shape_dist_traveled": "7.4360"}, {"shape_pt_lat": "30.366991", "shape_id": "38661", "shape_pt_lon": "-97.700602", "shape_pt_sequence": "299", "shape_dist_traveled": "7.4552"}, {"shape_pt_lat": "30.366713", "shape_id": "38661", "shape_pt_lon": "-97.700790", "shape_pt_sequence": "300", "shape_dist_traveled": "7.4910"}, {"shape_pt_lat": "30.365752", "shape_id": "38661", "shape_pt_lon": "-97.701398", "shape_pt_sequence": "301", "shape_dist_traveled": "7.6128"}, {"shape_pt_lat": "30.365698", "shape_id": "38661", "shape_pt_lon": "-97.701434", "shape_pt_sequence": "302", "shape_dist_traveled": "7.6200"}, {"shape_pt_lat": "30.365602", "shape_id": "38661", "shape_pt_lon": "-97.701495", "shape_pt_sequence": "303", "shape_dist_traveled": "7.6325"}, {"shape_pt_lat": "30.365467", "shape_id": "38661", "shape_pt_lon": "-97.701557", "shape_pt_sequence": "304", "shape_dist_traveled": "7.6487"}, {"shape_pt_lat": "30.365366", "shape_id": "38661", "shape_pt_lon": "-97.701609", "shape_pt_sequence": "305", "shape_dist_traveled": "7.6607"}, {"shape_pt_lat": "30.365259", "shape_id": "38661", "shape_pt_lon": "-97.701667", "shape_pt_sequence": "306", "shape_dist_traveled": "7.6737"}, {"shape_pt_lat": "30.364987", "shape_id": "38661", "shape_pt_lon": "-97.701091", "shape_pt_sequence": "307", "shape_dist_traveled": "7.7364"}, {"shape_pt_lat": "30.364617", "shape_id": "38661", "shape_pt_lon": "-97.700306", "shape_pt_sequence": "308", "shape_dist_traveled": "7.8227"}, {"shape_pt_lat": "30.364466", "shape_id": "38661", "shape_pt_lon": "-97.699987", "shape_pt_sequence": "309", "shape_dist_traveled": "7.8572"}, {"shape_pt_lat": "30.364439", "shape_id": "38661", "shape_pt_lon": "-97.699929", "shape_pt_sequence": "310", "shape_dist_traveled": "7.8639"}, {"shape_pt_lat": "30.364068", "shape_id": "38661", "shape_pt_lon": "-97.699156", "shape_pt_sequence": "311", "shape_dist_traveled": "7.9485"}, {"shape_pt_lat": "30.363775", "shape_id": "38661", "shape_pt_lon": "-97.698531", "shape_pt_sequence": "312", "shape_dist_traveled": "8.0165"}, {"shape_pt_lat": "30.363574", "shape_id": "38661", "shape_pt_lon": "-97.698104", "shape_pt_sequence": "313", "shape_dist_traveled": "8.0635"}, {"shape_pt_lat": "30.363399", "shape_id": "38661", "shape_pt_lon": "-97.697748", "shape_pt_sequence": "314", "shape_dist_traveled": "8.1025"}, {"shape_pt_lat": "30.363262", "shape_id": "38661", "shape_pt_lon": "-97.697467", "shape_pt_sequence": "315", "shape_dist_traveled": "8.1334"}, {"shape_pt_lat": "30.363061", "shape_id": "38661", "shape_pt_lon": "-97.697056", "shape_pt_sequence": "316", "shape_dist_traveled": "8.1787"}, {"shape_pt_lat": "30.362998", "shape_id": "38661", "shape_pt_lon": "-97.696905", "shape_pt_sequence": "317", "shape_dist_traveled": "8.1952"}, {"shape_pt_lat": "30.362734", "shape_id": "38661", "shape_pt_lon": "-97.696363", "shape_pt_sequence": "318", "shape_dist_traveled": "8.2547"}, {"shape_pt_lat": "30.362717", "shape_id": "38661", "shape_pt_lon": "-97.696328", "shape_pt_sequence": "319", "shape_dist_traveled": "8.2583"}, {"shape_pt_lat": "30.362593", "shape_id": "38661", "shape_pt_lon": "-97.696079", "shape_pt_sequence": "320", "shape_dist_traveled": "8.2861"}, {"shape_pt_lat": "30.362463", "shape_id": "38661", "shape_pt_lon": "-97.695824", "shape_pt_sequence": "321", "shape_dist_traveled": "8.3148"}, {"shape_pt_lat": "30.362350", "shape_id": "38661", "shape_pt_lon": "-97.695603", "shape_pt_sequence": "322", "shape_dist_traveled": "8.3395"}, {"shape_pt_lat": "30.362270", "shape_id": "38661", "shape_pt_lon": "-97.695455", "shape_pt_sequence": "323", "shape_dist_traveled": "8.3561"}, {"shape_pt_lat": "30.362132", "shape_id": "38661", "shape_pt_lon": "-97.695222", "shape_pt_sequence": "324", "shape_dist_traveled": "8.3828"}, {"shape_pt_lat": "30.362072", "shape_id": "38661", "shape_pt_lon": "-97.695131", "shape_pt_sequence": "325", "shape_dist_traveled": "8.3942"}, {"shape_pt_lat": "30.361984", "shape_id": "38661", "shape_pt_lon": "-97.694999", "shape_pt_sequence": "326", "shape_dist_traveled": "8.4100"}, {"shape_pt_lat": "30.361830", "shape_id": "38661", "shape_pt_lon": "-97.694780", "shape_pt_sequence": "327", "shape_dist_traveled": "8.4376"}, {"shape_pt_lat": "30.361766", "shape_id": "38661", "shape_pt_lon": "-97.694696", "shape_pt_sequence": "328", "shape_dist_traveled": "8.4483"}, {"shape_pt_lat": "30.361689", "shape_id": "38661", "shape_pt_lon": "-97.694597", "shape_pt_sequence": "329", "shape_dist_traveled": "8.4603"}, {"shape_pt_lat": "30.361603", "shape_id": "38661", "shape_pt_lon": "-97.694495", "shape_pt_sequence": "330", "shape_dist_traveled": "8.4744"}, {"shape_pt_lat": "30.361479", "shape_id": "38661", "shape_pt_lon": "-97.694340", "shape_pt_sequence": "331", "shape_dist_traveled": "8.4950"}, {"shape_pt_lat": "30.361365", "shape_id": "38661", "shape_pt_lon": "-97.694200", "shape_pt_sequence": "332", "shape_dist_traveled": "8.5127"}, {"shape_pt_lat": "30.361187", "shape_id": "38661", "shape_pt_lon": "-97.693986", "shape_pt_sequence": "333", "shape_dist_traveled": "8.5417"}, {"shape_pt_lat": "30.361016", "shape_id": "38661", "shape_pt_lon": "-97.693762", "shape_pt_sequence": "334", "shape_dist_traveled": "8.5700"}, {"shape_pt_lat": "30.360857", "shape_id": "38661", "shape_pt_lon": "-97.693532", "shape_pt_sequence": "335", "shape_dist_traveled": "8.5984"}, {"shape_pt_lat": "30.360834", "shape_id": "38661", "shape_pt_lon": "-97.693497", "shape_pt_sequence": "336", "shape_dist_traveled": "8.6029"}, {"shape_pt_lat": "30.360792", "shape_id": "38661", "shape_pt_lon": "-97.693430", "shape_pt_sequence": "337", "shape_dist_traveled": "8.6107"}, {"shape_pt_lat": "30.360698", "shape_id": "38661", "shape_pt_lon": "-97.693508", "shape_pt_sequence": "338", "shape_dist_traveled": "8.6229"}, {"shape_pt_lat": "30.360637", "shape_id": "38661", "shape_pt_lon": "-97.693556", "shape_pt_sequence": "339", "shape_dist_traveled": "8.6315"}, {"shape_pt_lat": "30.360558", "shape_id": "38661", "shape_pt_lon": "-97.693609", "shape_pt_sequence": "340", "shape_dist_traveled": "8.6418"}, {"shape_pt_lat": "30.360449", "shape_id": "38661", "shape_pt_lon": "-97.693676", "shape_pt_sequence": "341", "shape_dist_traveled": "8.6552"}, {"shape_pt_lat": "30.360280", "shape_id": "38661", "shape_pt_lon": "-97.693779", "shape_pt_sequence": "342", "shape_dist_traveled": "8.6767"}, {"shape_pt_lat": "30.360164", "shape_id": "38661", "shape_pt_lon": "-97.693854", "shape_pt_sequence": "343", "shape_dist_traveled": "8.6914"}, {"shape_pt_lat": "30.360043", "shape_id": "38661", "shape_pt_lon": "-97.693931", "shape_pt_sequence": "344", "shape_dist_traveled": "8.7067"}, {"shape_pt_lat": "30.359873", "shape_id": "38661", "shape_pt_lon": "-97.694043", "shape_pt_sequence": "345", "shape_dist_traveled": "8.7287"}, {"shape_pt_lat": "30.359667", "shape_id": "38661", "shape_pt_lon": "-97.694176", "shape_pt_sequence": "346", "shape_dist_traveled": "8.7546"}, {"shape_pt_lat": "30.359572", "shape_id": "38661", "shape_pt_lon": "-97.694238", "shape_pt_sequence": "347", "shape_dist_traveled": "8.7663"}, {"shape_pt_lat": "30.359453", "shape_id": "38661", "shape_pt_lon": "-97.694315", "shape_pt_sequence": "348", "shape_dist_traveled": "8.7824"}, {"shape_pt_lat": "30.359332", "shape_id": "38661", "shape_pt_lon": "-97.694390", "shape_pt_sequence": "349", "shape_dist_traveled": "8.7971"}, {"shape_pt_lat": "30.359226", "shape_id": "38661", "shape_pt_lon": "-97.694462", "shape_pt_sequence": "350", "shape_dist_traveled": "8.8110"}, {"shape_pt_lat": "30.359135", "shape_id": "38661", "shape_pt_lon": "-97.694520", "shape_pt_sequence": "351", "shape_dist_traveled": "8.8222"}, {"shape_pt_lat": "30.359045", "shape_id": "38661", "shape_pt_lon": "-97.694578", "shape_pt_sequence": "352", "shape_dist_traveled": "8.8339"}, {"shape_pt_lat": "30.358960", "shape_id": "38661", "shape_pt_lon": "-97.694634", "shape_pt_sequence": "353", "shape_dist_traveled": "8.8442"}, {"shape_pt_lat": "30.358883", "shape_id": "38661", "shape_pt_lon": "-97.694685", "shape_pt_sequence": "354", "shape_dist_traveled": "8.8545"}, {"shape_pt_lat": "30.358826", "shape_id": "38661", "shape_pt_lon": "-97.694724", "shape_pt_sequence": "355", "shape_dist_traveled": "8.8617"}, {"shape_pt_lat": "30.358774", "shape_id": "38661", "shape_pt_lon": "-97.694757", "shape_pt_sequence": "356", "shape_dist_traveled": "8.8684"}, {"shape_pt_lat": "30.358725", "shape_id": "38661", "shape_pt_lon": "-97.694790", "shape_pt_sequence": "357", "shape_dist_traveled": "8.8742"}, {"shape_pt_lat": "30.358681", "shape_id": "38661", "shape_pt_lon": "-97.694819", "shape_pt_sequence": "358", "shape_dist_traveled": "8.8801"}, {"shape_pt_lat": "30.358630", "shape_id": "38661", "shape_pt_lon": "-97.694845", "shape_pt_sequence": "359", "shape_dist_traveled": "8.8868"}, {"shape_pt_lat": "30.358579", "shape_id": "38661", "shape_pt_lon": "-97.694861", "shape_pt_sequence": "360", "shape_dist_traveled": "8.8928"}, {"shape_pt_lat": "30.358531", "shape_id": "38661", "shape_pt_lon": "-97.694870", "shape_pt_sequence": "361", "shape_dist_traveled": "8.8979"}, {"shape_pt_lat": "30.358460", "shape_id": "38661", "shape_pt_lon": "-97.694876", "shape_pt_sequence": "362", "shape_dist_traveled": "8.9060"}, {"shape_pt_lat": "30.358378", "shape_id": "38661", "shape_pt_lon": "-97.694876", "shape_pt_sequence": "363", "shape_dist_traveled": "8.9150"}, {"shape_pt_lat": "30.358298", "shape_id": "38661", "shape_pt_lon": "-97.694876", "shape_pt_sequence": "364", "shape_dist_traveled": "8.9240"}, {"shape_pt_lat": "30.358238", "shape_id": "38661", "shape_pt_lon": "-97.694878", "shape_pt_sequence": "365", "shape_dist_traveled": "8.9300"}, {"shape_pt_lat": "30.358199", "shape_id": "38661", "shape_pt_lon": "-97.694881", "shape_pt_sequence": "366", "shape_dist_traveled": "8.9350"}, {"shape_pt_lat": "30.358169", "shape_id": "38661", "shape_pt_lon": "-97.694886", "shape_pt_sequence": "367", "shape_dist_traveled": "8.9380"}, {"shape_pt_lat": "30.358134", "shape_id": "38661", "shape_pt_lon": "-97.694898", "shape_pt_sequence": "368", "shape_dist_traveled": "8.9425"}, {"shape_pt_lat": "30.358103", "shape_id": "38661", "shape_pt_lon": "-97.694915", "shape_pt_sequence": "369", "shape_dist_traveled": "8.9456"}, {"shape_pt_lat": "30.358053", "shape_id": "38661", "shape_pt_lon": "-97.694940", "shape_pt_sequence": "370", "shape_dist_traveled": "8.9523"}, {"shape_pt_lat": "30.357876", "shape_id": "38661", "shape_pt_lon": "-97.695047", "shape_pt_sequence": "371", "shape_dist_traveled": "8.9747"}, {"shape_pt_lat": "30.357719", "shape_id": "38661", "shape_pt_lon": "-97.695147", "shape_pt_sequence": "372", "shape_dist_traveled": "8.9944"}, {"shape_pt_lat": "30.357320", "shape_id": "38661", "shape_pt_lon": "-97.695405", "shape_pt_sequence": "373", "shape_dist_traveled": "9.0446"}, {"shape_pt_lat": "30.356796", "shape_id": "38661", "shape_pt_lon": "-97.695743", "shape_pt_sequence": "374", "shape_dist_traveled": "9.1122"}, {"shape_pt_lat": "30.355906", "shape_id": "38661", "shape_pt_lon": "-97.696323", "shape_pt_sequence": "375", "shape_dist_traveled": "9.2245"}, {"shape_pt_lat": "30.355702", "shape_id": "38661", "shape_pt_lon": "-97.696447", "shape_pt_sequence": "376", "shape_dist_traveled": "9.2505"}, {"shape_pt_lat": "30.355422", "shape_id": "38661", "shape_pt_lon": "-97.696629", "shape_pt_sequence": "377", "shape_dist_traveled": "9.2863"}, {"shape_pt_lat": "30.354620", "shape_id": "38661", "shape_pt_lon": "-97.697147", "shape_pt_sequence": "378", "shape_dist_traveled": "9.3884"}, {"shape_pt_lat": "30.354471", "shape_id": "38661", "shape_pt_lon": "-97.697241", "shape_pt_sequence": "379", "shape_dist_traveled": "9.4076"}, {"shape_pt_lat": "30.354388", "shape_id": "38661", "shape_pt_lon": "-97.697298", "shape_pt_sequence": "380", "shape_dist_traveled": "9.4179"}, {"shape_pt_lat": "30.354327", "shape_id": "38661", "shape_pt_lon": "-97.697344", "shape_pt_sequence": "381", "shape_dist_traveled": "9.4260"}, {"shape_pt_lat": "30.354281", "shape_id": "38661", "shape_pt_lon": "-97.697384", "shape_pt_sequence": "382", "shape_dist_traveled": "9.4324"}, {"shape_pt_lat": "30.354256", "shape_id": "38661", "shape_pt_lon": "-97.697415", "shape_pt_sequence": "383", "shape_dist_traveled": "9.4366"}, {"shape_pt_lat": "30.354232", "shape_id": "38661", "shape_pt_lon": "-97.697455", "shape_pt_sequence": "384", "shape_dist_traveled": "9.4411"}, {"shape_pt_lat": "30.354213", "shape_id": "38661", "shape_pt_lon": "-97.697503", "shape_pt_sequence": "385", "shape_dist_traveled": "9.4465"}, {"shape_pt_lat": "30.354192", "shape_id": "38661", "shape_pt_lon": "-97.697593", "shape_pt_sequence": "386", "shape_dist_traveled": "9.4550"}, {"shape_pt_lat": "30.354170", "shape_id": "38661", "shape_pt_lon": "-97.697680", "shape_pt_sequence": "387", "shape_dist_traveled": "9.4643"}, {"shape_pt_lat": "30.354147", "shape_id": "38661", "shape_pt_lon": "-97.697779", "shape_pt_sequence": "388", "shape_dist_traveled": "9.4738"}, {"shape_pt_lat": "30.354046", "shape_id": "38661", "shape_pt_lon": "-97.698126", "shape_pt_sequence": "389", "shape_dist_traveled": "9.5085"}, {"shape_pt_lat": "30.353983", "shape_id": "38661", "shape_pt_lon": "-97.698275", "shape_pt_sequence": "390", "shape_dist_traveled": "9.5251"}, {"shape_pt_lat": "30.353943", "shape_id": "38661", "shape_pt_lon": "-97.698349", "shape_pt_sequence": "391", "shape_dist_traveled": "9.5332"}, {"shape_pt_lat": "30.353894", "shape_id": "38661", "shape_pt_lon": "-97.698414", "shape_pt_sequence": "392", "shape_dist_traveled": "9.5416"}, {"shape_pt_lat": "30.353515", "shape_id": "38661", "shape_pt_lon": "-97.698760", "shape_pt_sequence": "393", "shape_dist_traveled": "9.5951"}, {"shape_pt_lat": "30.353130", "shape_id": "38661", "shape_pt_lon": "-97.699066", "shape_pt_sequence": "394", "shape_dist_traveled": "9.6475"}, {"shape_pt_lat": "30.352780", "shape_id": "38661", "shape_pt_lon": "-97.699344", "shape_pt_sequence": "395", "shape_dist_traveled": "9.6944"}, {"shape_pt_lat": "30.352125", "shape_id": "38661", "shape_pt_lon": "-97.699903", "shape_pt_sequence": "396", "shape_dist_traveled": "9.7844"}, {"shape_pt_lat": "30.351045", "shape_id": "38661", "shape_pt_lon": "-97.700800", "shape_pt_sequence": "397", "shape_dist_traveled": "9.9320"}, {"shape_pt_lat": "30.350205", "shape_id": "38661", "shape_pt_lon": "-97.701522", "shape_pt_sequence": "398", "shape_dist_traveled": "10.0478"}, {"shape_pt_lat": "30.350071", "shape_id": "38661", "shape_pt_lon": "-97.701638", "shape_pt_sequence": "399", "shape_dist_traveled": "10.0670"}, {"shape_pt_lat": "30.349991", "shape_id": "38661", "shape_pt_lon": "-97.701706", "shape_pt_sequence": "400", "shape_dist_traveled": "10.0778"}, {"shape_pt_lat": "30.349667", "shape_id": "38661", "shape_pt_lon": "-97.701976", "shape_pt_sequence": "401", "shape_dist_traveled": "10.1222"}, {"shape_pt_lat": "30.349585", "shape_id": "38661", "shape_pt_lon": "-97.702039", "shape_pt_sequence": "402", "shape_dist_traveled": "10.1330"}, {"shape_pt_lat": "30.349522", "shape_id": "38661", "shape_pt_lon": "-97.702081", "shape_pt_sequence": "403", "shape_dist_traveled": "10.1411"}, {"shape_pt_lat": "30.349133", "shape_id": "38661", "shape_pt_lon": "-97.702308", "shape_pt_sequence": "404", "shape_dist_traveled": "10.1894"}, {"shape_pt_lat": "30.349003", "shape_id": "38661", "shape_pt_lon": "-97.702389", "shape_pt_sequence": "405", "shape_dist_traveled": "10.2064"}, {"shape_pt_lat": "30.348341", "shape_id": "38661", "shape_pt_lon": "-97.702780", "shape_pt_sequence": "406", "shape_dist_traveled": "10.2882"}, {"shape_pt_lat": "30.347949", "shape_id": "38661", "shape_pt_lon": "-97.703002", "shape_pt_sequence": "407", "shape_dist_traveled": "10.3374"}, {"shape_pt_lat": "30.347704", "shape_id": "38661", "shape_pt_lon": "-97.703134", "shape_pt_sequence": "408", "shape_dist_traveled": "10.3670"}, {"shape_pt_lat": "30.347559", "shape_id": "38661", "shape_pt_lon": "-97.703206", "shape_pt_sequence": "409", "shape_dist_traveled": "10.3844"}, {"shape_pt_lat": "30.347443", "shape_id": "38661", "shape_pt_lon": "-97.703262", "shape_pt_sequence": "410", "shape_dist_traveled": "10.3988"}, {"shape_pt_lat": "30.346896", "shape_id": "38661", "shape_pt_lon": "-97.703556", "shape_pt_sequence": "411", "shape_dist_traveled": "10.4659"}, {"shape_pt_lat": "30.346694", "shape_id": "38661", "shape_pt_lon": "-97.703674", "shape_pt_sequence": "412", "shape_dist_traveled": "10.4905"}, {"shape_pt_lat": "30.346310", "shape_id": "38661", "shape_pt_lon": "-97.703882", "shape_pt_sequence": "413", "shape_dist_traveled": "10.5379"}, {"shape_pt_lat": "30.346135", "shape_id": "38661", "shape_pt_lon": "-97.703970", "shape_pt_sequence": "414", "shape_dist_traveled": "10.5589"}, {"shape_pt_lat": "30.346062", "shape_id": "38661", "shape_pt_lon": "-97.704009", "shape_pt_sequence": "415", "shape_dist_traveled": "10.5675"}, {"shape_pt_lat": "30.346015", "shape_id": "38661", "shape_pt_lon": "-97.704029", "shape_pt_sequence": "416", "shape_dist_traveled": "10.5738"}, {"shape_pt_lat": "30.345350", "shape_id": "38661", "shape_pt_lon": "-97.704336", "shape_pt_sequence": "417", "shape_dist_traveled": "10.6536"}, {"shape_pt_lat": "30.345046", "shape_id": "38661", "shape_pt_lon": "-97.704469", "shape_pt_sequence": "418", "shape_dist_traveled": "10.6888"}, {"shape_pt_lat": "30.345018", "shape_id": "38661", "shape_pt_lon": "-97.704511", "shape_pt_sequence": "419", "shape_dist_traveled": "10.6938"}, {"shape_pt_lat": "30.344662", "shape_id": "38661", "shape_pt_lon": "-97.704737", "shape_pt_sequence": "420", "shape_dist_traveled": "10.7394"}, {"shape_pt_lat": "30.344534", "shape_id": "38661", "shape_pt_lon": "-97.704816", "shape_pt_sequence": "421", "shape_dist_traveled": "10.7555"}, {"shape_pt_lat": "30.344443", "shape_id": "38661", "shape_pt_lon": "-97.704871", "shape_pt_sequence": "422", "shape_dist_traveled": "10.7667"}, {"shape_pt_lat": "30.344381", "shape_id": "38661", "shape_pt_lon": "-97.704914", "shape_pt_sequence": "423", "shape_dist_traveled": "10.7748"}, {"shape_pt_lat": "30.344293", "shape_id": "38661", "shape_pt_lon": "-97.704989", "shape_pt_sequence": "424", "shape_dist_traveled": "10.7870"}, {"shape_pt_lat": "30.344109", "shape_id": "38661", "shape_pt_lon": "-97.705150", "shape_pt_sequence": "425", "shape_dist_traveled": "10.8126"}, {"shape_pt_lat": "30.343998", "shape_id": "38661", "shape_pt_lon": "-97.705256", "shape_pt_sequence": "426", "shape_dist_traveled": "10.8290"}, {"shape_pt_lat": "30.343851", "shape_id": "38661", "shape_pt_lon": "-97.705393", "shape_pt_sequence": "427", "shape_dist_traveled": "10.8496"}, {"shape_pt_lat": "30.343775", "shape_id": "38661", "shape_pt_lon": "-97.705463", "shape_pt_sequence": "428", "shape_dist_traveled": "10.8602"}, {"shape_pt_lat": "30.343286", "shape_id": "38661", "shape_pt_lon": "-97.705860", "shape_pt_sequence": "429", "shape_dist_traveled": "10.9271"}, {"shape_pt_lat": "30.343272", "shape_id": "38661", "shape_pt_lon": "-97.705869", "shape_pt_sequence": "430", "shape_dist_traveled": "10.9285"}, {"shape_pt_lat": "30.343140", "shape_id": "38661", "shape_pt_lon": "-97.705878", "shape_pt_sequence": "431", "shape_dist_traveled": "10.9435"}, {"shape_pt_lat": "30.343034", "shape_id": "38661", "shape_pt_lon": "-97.705957", "shape_pt_sequence": "432", "shape_dist_traveled": "10.9574"}, {"shape_pt_lat": "30.342884", "shape_id": "38661", "shape_pt_lon": "-97.706064", "shape_pt_sequence": "433", "shape_dist_traveled": "10.9769"}, {"shape_pt_lat": "30.342742", "shape_id": "38661", "shape_pt_lon": "-97.706176", "shape_pt_sequence": "434", "shape_dist_traveled": "10.9957"}, {"shape_pt_lat": "30.342700", "shape_id": "38661", "shape_pt_lon": "-97.706210", "shape_pt_sequence": "435", "shape_dist_traveled": "11.0021"}, {"shape_pt_lat": "30.342523", "shape_id": "38661", "shape_pt_lon": "-97.706363", "shape_pt_sequence": "436", "shape_dist_traveled": "11.0257"}, {"shape_pt_lat": "30.342354", "shape_id": "38661", "shape_pt_lon": "-97.706532", "shape_pt_sequence": "437", "shape_dist_traveled": "11.0512"}, {"shape_pt_lat": "30.342302", "shape_id": "38661", "shape_pt_lon": "-97.706590", "shape_pt_sequence": "438", "shape_dist_traveled": "11.0590"}, {"shape_pt_lat": "30.342268", "shape_id": "38661", "shape_pt_lon": "-97.706638", "shape_pt_sequence": "439", "shape_dist_traveled": "11.0654"}, {"shape_pt_lat": "30.342249", "shape_id": "38661", "shape_pt_lon": "-97.706664", "shape_pt_sequence": "440", "shape_dist_traveled": "11.0683"}, {"shape_pt_lat": "30.342191", "shape_id": "38661", "shape_pt_lon": "-97.706763", "shape_pt_sequence": "441", "shape_dist_traveled": "11.0799"}, {"shape_pt_lat": "30.342107", "shape_id": "38661", "shape_pt_lon": "-97.706934", "shape_pt_sequence": "442", "shape_dist_traveled": "11.0988"}, {"shape_pt_lat": "30.342048", "shape_id": "38661", "shape_pt_lon": "-97.707032", "shape_pt_sequence": "443", "shape_dist_traveled": "11.1105"}, {"shape_pt_lat": "30.341983", "shape_id": "38661", "shape_pt_lon": "-97.707116", "shape_pt_sequence": "444", "shape_dist_traveled": "11.1211"}, {"shape_pt_lat": "30.341909", "shape_id": "38661", "shape_pt_lon": "-97.707193", "shape_pt_sequence": "445", "shape_dist_traveled": "11.1325"}, {"shape_pt_lat": "30.341596", "shape_id": "38661", "shape_pt_lon": "-97.707516", "shape_pt_sequence": "446", "shape_dist_traveled": "11.1785"}, {"shape_pt_lat": "30.341276", "shape_id": "38661", "shape_pt_lon": "-97.707851", "shape_pt_sequence": "447", "shape_dist_traveled": "11.2267"}, {"shape_pt_lat": "30.341027", "shape_id": "38661", "shape_pt_lon": "-97.708104", "shape_pt_sequence": "448", "shape_dist_traveled": "11.2635"}, {"shape_pt_lat": "30.340896", "shape_id": "38661", "shape_pt_lon": "-97.708237", "shape_pt_sequence": "449", "shape_dist_traveled": "11.2826"}, {"shape_pt_lat": "30.340545", "shape_id": "38661", "shape_pt_lon": "-97.708605", "shape_pt_sequence": "450", "shape_dist_traveled": "11.3357"}, {"shape_pt_lat": "30.339570", "shape_id": "38661", "shape_pt_lon": "-97.709630", "shape_pt_sequence": "451", "shape_dist_traveled": "11.4816"}, {"shape_pt_lat": "30.339206", "shape_id": "38661", "shape_pt_lon": "-97.709982", "shape_pt_sequence": "452", "shape_dist_traveled": "11.5348"}, {"shape_pt_lat": "30.338913", "shape_id": "38661", "shape_pt_lon": "-97.710265", "shape_pt_sequence": "453", "shape_dist_traveled": "11.5767"}, {"shape_pt_lat": "30.339406", "shape_id": "38661", "shape_pt_lon": "-97.711331", "shape_pt_sequence": "454", "shape_dist_traveled": "11.6926"}, {"shape_pt_lat": "30.339843", "shape_id": "38661", "shape_pt_lon": "-97.712125", "shape_pt_sequence": "455", "shape_dist_traveled": "11.7825"}, {"shape_pt_lat": "30.340169", "shape_id": "38661", "shape_pt_lon": "-97.712873", "shape_pt_sequence": "456", "shape_dist_traveled": "11.8630"}, {"shape_pt_lat": "30.339379", "shape_id": "38661", "shape_pt_lon": "-97.713397", "shape_pt_sequence": "457", "shape_dist_traveled": "11.9638"}, {"shape_pt_lat": "30.338601", "shape_id": "38661", "shape_pt_lon": "-97.713896", "shape_pt_sequence": "458", "shape_dist_traveled": "12.0627"}, {"shape_pt_lat": "30.338208", "shape_id": "38661", "shape_pt_lon": "-97.714153", "shape_pt_sequence": "459", "shape_dist_traveled": "12.1124"}, {"shape_pt_lat": "30.337808", "shape_id": "38661", "shape_pt_lon": "-97.714415", "shape_pt_sequence": "460", "shape_dist_traveled": "12.1639"}, {"shape_pt_lat": "30.337414", "shape_id": "38661", "shape_pt_lon": "-97.714677", "shape_pt_sequence": "461", "shape_dist_traveled": "12.2145"}, {"shape_pt_lat": "30.336526", "shape_id": "38661", "shape_pt_lon": "-97.715264", "shape_pt_sequence": "462", "shape_dist_traveled": "12.3279"}, {"shape_pt_lat": "30.335628", "shape_id": "38661", "shape_pt_lon": "-97.715847", "shape_pt_sequence": "463", "shape_dist_traveled": "12.4425"}, {"shape_pt_lat": "30.334792", "shape_id": "38661", "shape_pt_lon": "-97.716402", "shape_pt_sequence": "464", "shape_dist_traveled": "12.5495"}, {"shape_pt_lat": "30.334430", "shape_id": "38661", "shape_pt_lon": "-97.716649", "shape_pt_sequence": "465", "shape_dist_traveled": "12.5962"}, {"shape_pt_lat": "30.334182", "shape_id": "38661", "shape_pt_lon": "-97.716818", "shape_pt_sequence": "466", "shape_dist_traveled": "12.6276"}, {"shape_pt_lat": "30.333999", "shape_id": "38661", "shape_pt_lon": "-97.716946", "shape_pt_sequence": "467", "shape_dist_traveled": "12.6518"}, {"shape_pt_lat": "30.333682", "shape_id": "38661", "shape_pt_lon": "-97.716793", "shape_pt_sequence": "468", "shape_dist_traveled": "12.6895"}, {"shape_pt_lat": "30.333582", "shape_id": "38661", "shape_pt_lon": "-97.716746", "shape_pt_sequence": "469", "shape_dist_traveled": "12.7015"}, {"shape_pt_lat": "30.332483", "shape_id": "38661", "shape_pt_lon": "-97.716172", "shape_pt_sequence": "470", "shape_dist_traveled": "12.8354"}, {"shape_pt_lat": "30.332311", "shape_id": "38661", "shape_pt_lon": "-97.716087", "shape_pt_sequence": "471", "shape_dist_traveled": "12.8560"}, {"shape_pt_lat": "30.332225", "shape_id": "38661", "shape_pt_lon": "-97.716044", "shape_pt_sequence": "472", "shape_dist_traveled": "12.8667"}, {"shape_pt_lat": "30.332117", "shape_id": "38661", "shape_pt_lon": "-97.715996", "shape_pt_sequence": "473", "shape_dist_traveled": "12.8797"}, {"shape_pt_lat": "30.331959", "shape_id": "38661", "shape_pt_lon": "-97.715935", "shape_pt_sequence": "474", "shape_dist_traveled": "12.8978"}, {"shape_pt_lat": "30.331789", "shape_id": "38661", "shape_pt_lon": "-97.715872", "shape_pt_sequence": "475", "shape_dist_traveled": "12.9177"}, {"shape_pt_lat": "30.331610", "shape_id": "38661", "shape_pt_lon": "-97.715812", "shape_pt_sequence": "476", "shape_dist_traveled": "12.9383"}, {"shape_pt_lat": "30.331450", "shape_id": "38661", "shape_pt_lon": "-97.715765", "shape_pt_sequence": "477", "shape_dist_traveled": "12.9570"}, {"shape_pt_lat": "30.331303", "shape_id": "38661", "shape_pt_lon": "-97.715727", "shape_pt_sequence": "478", "shape_dist_traveled": "12.9735"}, {"shape_pt_lat": "30.331171", "shape_id": "38661", "shape_pt_lon": "-97.715701", "shape_pt_sequence": "479", "shape_dist_traveled": "12.9886"}, {"shape_pt_lat": "30.331000", "shape_id": "38661", "shape_pt_lon": "-97.715672", "shape_pt_sequence": "480", "shape_dist_traveled": "13.0079"}, {"shape_pt_lat": "30.330867", "shape_id": "38661", "shape_pt_lon": "-97.715656", "shape_pt_sequence": "481", "shape_dist_traveled": "13.0229"}, {"shape_pt_lat": "30.330748", "shape_id": "38661", "shape_pt_lon": "-97.715650", "shape_pt_sequence": "482", "shape_dist_traveled": "13.0359"}, {"shape_pt_lat": "30.330378", "shape_id": "38661", "shape_pt_lon": "-97.715662", "shape_pt_sequence": "483", "shape_dist_traveled": "13.0769"}, {"shape_pt_lat": "30.330183", "shape_id": "38661", "shape_pt_lon": "-97.715674", "shape_pt_sequence": "484", "shape_dist_traveled": "13.0990"}, {"shape_pt_lat": "30.329750", "shape_id": "38661", "shape_pt_lon": "-97.715719", "shape_pt_sequence": "485", "shape_dist_traveled": "13.1472"}, {"shape_pt_lat": "30.329325", "shape_id": "38661", "shape_pt_lon": "-97.715776", "shape_pt_sequence": "486", "shape_dist_traveled": "13.1945"}, {"shape_pt_lat": "30.328967", "shape_id": "38661", "shape_pt_lon": "-97.715825", "shape_pt_sequence": "487", "shape_dist_traveled": "13.2348"}, {"shape_pt_lat": "30.328908", "shape_id": "38661", "shape_pt_lon": "-97.715833", "shape_pt_sequence": "488", "shape_dist_traveled": "13.2409"}, {"shape_pt_lat": "30.328846", "shape_id": "38661", "shape_pt_lon": "-97.715842", "shape_pt_sequence": "489", "shape_dist_traveled": "13.2480"}, {"shape_pt_lat": "30.328816", "shape_id": "38661", "shape_pt_lon": "-97.715589", "shape_pt_sequence": "490", "shape_dist_traveled": "13.2731"}, {"shape_pt_lat": "30.328755", "shape_id": "38661", "shape_pt_lon": "-97.715050", "shape_pt_sequence": "491", "shape_dist_traveled": "13.3246"}, {"shape_pt_lat": "30.328629", "shape_id": "38661", "shape_pt_lon": "-97.713821", "shape_pt_sequence": "492", "shape_dist_traveled": "13.4434"}]
