[{"stop_lat": 30.257382, "stop_timezone": null, "wheelchair_boarding": 0, "stop_code": "2803", "direction_id": 0, "stop_lon": -97.710836, "parent_station": null, "route_id": "122", "stop_url": null, "stop_sequence": 1, "stop_id": "2803", "stop_desc": "000500 PLEASANT VALLEY & 5TH", "stop_name": "500 PLEASANT VALLEY/5TH (CAPMETRO)", "location_type": null, "platform_code": null, "zone_id": null}, {"stop_lat": 30.25666, "stop_timezone": null, "wheelchair_boarding": 0, "stop_code": "1843", "direction_id": 0, "stop_lon": -97.72009, "parent_station": null, "route_id": "122", "stop_url": null, "stop_sequence": 2, "stop_id": "1843", "stop_desc": "002200 2ND & ROBERT T MARTINEZ JR", "stop_name": "2200 2ND/ROBERT T MARTINEZ JR", "location_type": null, "platform_code": null, "zone_id": null}, {"stop_lat": 30.262441, "stop_timezone": null, "wheelchair_boarding": 0, "stop_code": "5933", "direction_id": 0, "stop_lon": -97.738607, "parent_station": null, "route_id": "122", "stop_url": null, "stop_sequence": 3, "stop_id": "5933", "stop_desc": "000119 RED RIVER & CESAR CHAVEZ", "stop_name": "119 RED RIVER/CESAR CHAVEZ", "location_type": null, "platform_code": null, "zone_id": null}, {"stop_lat": 30.265282, "stop_timezone": null, "wheelchair_boarding": 0, "stop_code": "5591", "direction_id": 0, "stop_lon": -97.739827, "parent_station": null, "route_id": "122", "stop_url": null, "stop_sequence": 4, "stop_id": "5591", "stop_desc": "000400 4TH & TRINITY", "stop_name": "400 4TH/TRINITY", "location_type": null, "platform_code": null, "zone_id": null}, {"stop_lat": 30.266225, "stop_timezone": null, "wheelchair_boarding": 0, "stop_code": "5599", "direction_id": 0, "stop_lon": -97.743326, "parent_station": null, "route_id": "122", "stop_url": null, "stop_sequence": 5, "stop_id": "5599", "stop_desc": "000100 4TH & CONGRESS", "stop_name": "100 4TH/CONGRESS", "location_type": null, "platform_code": null, "zone_id": null}, {"stop_lat": 30.26908, "stop_timezone": null, "wheelchair_boarding": 0, "stop_code": "1966", "direction_id": 0, "stop_lon": -97.74609, "parent_station": null, "route_id": "122", "stop_url": null, "stop_sequence": 6, "stop_id": "1966", "stop_desc": "000300 6TH & GUADALUPE", "stop_name": "6TH/GUADALUPE", "location_type": null, "platform_code": null, "zone_id": null}, {"stop_lat": 30.271955, "stop_timezone": null, "wheelchair_boarding": 0, "stop_code": "1971", "direction_id": 0, "stop_lon": -97.754879, "parent_station": null, "route_id": "122", "stop_url": null, "stop_sequence": 7, "stop_id": "1971", "stop_desc": "001000 6TH & BAYLOR", "stop_name": "6TH/BAYLOR", "location_type": null, "platform_code": null, "zone_id": null}, {"stop_lat": 30.274836, "stop_timezone": null, "wheelchair_boarding": 0, "stop_code": "1974", "direction_id": 0, "stop_lon": -97.762509, "parent_station": null, "route_id": "122", "stop_url": null, "stop_sequence": 8, "stop_id": "1974", "stop_desc": "001514 6TH & WEST LYNN", "stop_name": "6TH/WEST LYNN", "location_type": null, "platform_code": null, "zone_id": null}, {"stop_lat": 30.393268, "stop_timezone": null, "wheelchair_boarding": 0, "stop_code": "3329", "direction_id": 0, "stop_lon": -97.837839, "parent_station": null, "route_id": "122", "stop_url": null, "stop_sequence": 9, "stop_id": "3329", "stop_desc": "000000 MCNEIL & FM 2222", "stop_name": "3M COMPANY AT SKYWALK", "location_type": null, "platform_code": null, "zone_id": null}, {"stop_lat": 30.40602, "stop_timezone": null, "wheelchair_boarding": 0, "stop_code": "4601", "direction_id": 0, "stop_lon": -97.85079, "parent_station": null, "route_id": "122", "stop_url": null, "stop_sequence": 10, "stop_id": "4601", "stop_desc": "011400 FOUR POINTS & FM 620", "stop_name": "11400 FOUR POINTS/FM 620", "location_type": null, "platform_code": null, "zone_id": null}, {"stop_lat": 30.480719, "stop_timezone": null, "wheelchair_boarding": 0, "stop_code": "5230", "direction_id": 0, "stop_lon": -97.786775, "parent_station": null, "route_id": "122", "stop_url": null, "stop_sequence": 11, "stop_id": "5230", "stop_desc": "10900G LYNDHURST & LAKELINE", "stop_name": "LAKELINE STATION BAY G", "location_type": null, "platform_code": null, "zone_id": null}]
